Workbook
Name UPDATE: 'Data Sheet'!$E$1
Name UPDATE: #REF!

Sheet Dashboard
C1: ='Data Sheet'!B1& " - FINANCIAL MODEL DASHBOARD" -> TITAN COMPANY LTD - FINANCIAL MODEL DASHBOARD | S1: KEY RATIOS SCORECARD
S2: Metric | U2: FY26 | V2: Hist. avg | W2: vs avg
S3: ='Ratio Analysis'!B5 -> Sales Growth | U3: ='Ratio Analysis'!L5 -> 0.44872304 | V3: ='Ratio Analysis'!N5 -> 0.24063785 | W3: =IF(U3>V3,"▲","▼") -> ▲
S4: ='Ratio Analysis'!B12 -> EBITDA Margin | U4: ='Ratio Analysis'!L12 -> 0.095416971 | V4: ='Ratio Analysis'!N12 -> 0.10169001 | W4: =IF(U4>V4,"▲","▼") -> ▼
S5: ='Ratio Analysis'!B15 -> Net Profit Margin | U5: ='Ratio Analysis'!L15 -> 0.057921538 | V5: ='Ratio Analysis'!N15 -> 0.064811348 | W5: =IF(U5>V5,"▲","▼") -> ▼
S6: ROCE | U6: ='Ratio Analysis'!L21 -> 0.16257232 | V6: ='Ratio Analysis'!N21 -> 0.18139912 | W6: =IF(U6>V6,"▲","▼") -> ▼
S7: ROE | U7: ='Ratio Analysis'!L23 -> 0.32305929 | V7: ='Ratio Analysis'!N23 -> 0.24664543 | W7: =IF(U7>V7,"▲","▼") -> ▲
S8: ='Ratio Analysis'!B24 -> Sustainable Growth Rate | U8: ='Ratio Analysis'!L24 -> 0.23804369 | V8: ='Ratio Analysis'!N24 -> 0.1752197 | W8: =IF(U8>V8,"▲","▼") -> ▲
S9: ='Ratio Analysis'!B25 -> Interest Coverage Ratio | U9: ='Ratio Analysis'!L25 -> 6.3822034 | V9: ='Ratio Analysis'!N25 -> 15.828528 | W9: =IF(U9>V9,"▲","▼") -> ▼
S10: ='Ratio Analysis'!B36 -> Inventory Days | U10: ='Ratio Analysis'!L36 -> 212.37384 | V10: ='Ratio Analysis'!N36 -> 184.08999 | W10: =IF(U10>V10,"▲","▼") -> ▲
S11: ▲▼ = FY26 vs historical average (Ratio Analysis). Inventory days: lower is better.
F12: =AVERAGE('Historical FS'!D6:L6) -> 0.24063785
M13: =AVERAGE('Historical FS'!C18:L18) -> 0.10169001 | S13: MARGINS & RETURNS FY17–FY26
N16: FY27 EBITDA SENSITIVITY (₹ Cr)
L18: Base Sales FY27 | N18: ='Projections '!L6*(1+Dashboard!Q18) -> 108023.86 | O18: ='Sensitivity Analysis'!B3 -> Sales Growth Rate | Q18: ='Sensitivity Analysis'!G3 -> 0.2333743
L19: Base EBITDA FY27 | N19: =N18*Q19 -> 10403.428 | O19: ='Sensitivity Analysis'!B4 -> EBITDA Margin | Q19: ='Sensitivity Analysis'!G4 -> 0.096306769
L22: =N19 -> 10403.428 | M22: =N22-0.05 -> 0.1333743 | N22: =O22-0.05 -> 0.1833743 | O22: ='Projections '!$M$7 -> 0.2333743 | P22: =O22+0.05 -> 0.2833743 | Q22: =P22+0.05 -> 0.3333743
L23: =L24-0.02 -> 0.056306769 | M23: 5589.317 | N23: 5835.8956 | O23: 6082.4742 | P23: 6329.0528 | Q23: 6575.6314
L24: =L25-0.02 -> 0.076306769 | M24: 7574.6261 | N24: 7908.7887 | O24: 8242.9513 | P24: 8577.1139 | Q24: 8911.2765
L25: ='Projections '!$M$29 -> 0.096306769 | M25: 9559.9352 | N25: 9981.6818 | O25: 10403.428 | P25: 10825.175 | Q25: 11246.922
L26: =L25+0.02 -> 0.11630677 | M26: 11545.244 | N26: 12054.575 | O26: 12563.906 | P26: 13073.236 | Q26: 13582.567
L27: =L26+0.02 -> 0.13630677 | M27: 13530.553 | N27: 14127.468 | O27: 14724.383 | P27: 15321.297 | Q27: 15918.212
L29: Range: | M29: ="₹"&TEXT(MIN(M23:Q27),"#,##0")&"- ₹"&TEXT(MAX(M23:Q27),"#,##0") -> ₹5,589- ₹15,918
L30: Vs Base : | M30: =TEXT((M23-O25)/O25,"+0%;-0%")& " / " &TEXT((Q27-O25)/O25,"+0%;-0%") -> -46% / +53%
B34: KEY TAKEAWAYS (FY26)
B35: • Sales were ₹87,584 Cr in FY26, up 44.9% YoY against a historical average of 24.1%. Sales CAGR for FY17–FY26 is 23.3%.
B36: • EBITDA was ₹8,357 Cr (+46.8% YoY) at a 9.5% margin vs a 10.2% average. Gross margin was 16.1% (average 19.3%) and selling & general expenses were 6.6% of sales (average 9.1%).
B37: • Net profit was ₹5,073 Cr (+52.0% YoY) and EPS was ₹57.0 vs ₹37.5 a year earlier. Net margin was 5.8% against a 6.5% average.
B38: • ROE was 32.3% (average 24.7%) and ROCE was 16.3% (average 18.1%). The sustainable growth rate is 23.8% (average 17.5%).
B39: • Interest coverage was 6.4x (average 15.8x) and inventory days were 212 (average 184).
B40: • Dividend per share was ₹15.0 (prior year ₹11.0), a payout of 26.3% vs a 29.6% average.
B43: ASSUMPTIONS & NOTES
B44: • Forecast method: sales – Arithmetic Mean method; EBITDA – Arithmetic Mean method. Implied FY27E growth is 24.1% for sales and 28.7% for EBITDA.
B45: • Implied EBITDA margin moves from 9.9% in FY27E to 11.9% in FY32E, against a historical range of 8.0% to 12.0%.
B46: • FY26 sales growth was 44.9% against a historical average of 24.1%. Forecasts compound from the FY26 base, so a high-growth base year can lift every forecast year.
B47: • Ratios use year-end balances, not averages.

Sheet Data Sheet
A1: COMPANY NAME | B1: TITAN COMPANY LTD | E1: =IF(B2<>B3, "A NEW VERSION OF THE WORKSHEET IS AVAILABLE", "")
A2: LATEST VERSION | B2: 2.1 | E2: PLEASE DO NOT MAKE ANY CHANGES TO THIS SHEET
A3: CURRENT VERSION | B3: 2.1
A5: META
A6: Number of shares | B6: =IF(B9>0, B9/B8, 0) -> 88.778612
A7: Face Value | B7: 1
A8: Current Price | B8: 4998.7
A9: Market Capitalization | B9: 443777.65
A15: PROFIT & LOSS
A16: Report Date | B16: 42825 | C16: 43190 | D16: 43555 | E16: 43921 | F16: 44286 | G16: 44651 | H16: 45016 | I16: 45382 | J16: 45747 | K16: 46112
A17: Sales | B17: 13260.83 | C17: 16119.77 | D17: 19778.52 | E17: 21052 | F17: 21644 | G17: 28799 | H17: 40575 | I17: 51084 | J17: 60456 | K17: 87584
A18: Raw Material Cost | B18: 9821.14 | C18: 12664.83 | D18: 15170.66 | E18: 16033 | F18: 16292 | G18: 26436 | H18: 32589 | I18: 42103 | J18: 55271 | K18: 80243
A19: Change in Inventory | B19: 313.71 | C19: 978.61 | D19: 776.41 | E19: 878 | F19: -122 | G19: 4795 | H19: 2234 | I19: 2671 | J19: 7815 | K19: 9936
A20: Power and Fuel | B20: 43.84 | C20: 45.32 | D20: 48.51 | E20: 52 | F20: 37 | G20: 45 | H20: 59 | I20: 71 | J20: 78 | K20: 87
A21: Other Mfr. Exp | B21: 160.42 | C21: 124.83 | D21: 193.28 | E21: 215 | F21: 141 | G21: 183 | H21: 225 | I21: 286 | J21: 326 | K21: 375
A22: Employee Cost | B22: 894.32 | C22: 906.26 | D22: 1024.44 | E22: 1204 | F22: 1069 | G22: 1356 | H22: 1656 | I22: 1875 | J22: 2164 | K22: 2692
A23: Selling and admin | B23: 1211.16 | C23: 1277.81 | D23: 1454.32 | E23: 1470 | F23: 1029 | G23: 1697 | H23: 2715 | I23: 3249 | J23: 3494 | K23: 4185
A24: Other Expenses | B24: 279.76 | C24: 435.13 | D24: 669.93 | E24: 493 | F24: 1229 | G24: 533 | H24: 683 | I24: 879 | J24: 1244 | K24: 1581
A25: Other Income | B25: -42.38 | C25: 69.93 | D25: 178.48 | E25: 153 | F25: 180 | G25: 177 | H25: 306 | I25: 534 | J25: 487 | K25: 450
A26: Depreciation | B26: 110.53 | C26: 131.43 | D26: 162.84 | E26: 348 | F26: 375 | G26: 399 | H26: 441 | I26: 584 | J26: 693 | K26: 826
A27: Interest | B27: 37.74 | C27: 52.92 | D27: 52.54 | E27: 166 | F27: 203 | G27: 218 | H27: 300 | I27: 619 | J27: 953 | K27: 1180
... A31: Dividend Amount | B31: 230.83 | C31: 332.92 | D31: 443.9 | E31: 356 | F31: 356 | G31: 667.5 | H31: 890 | I31: 979 | J31: 979 | K31: 1335
A40: Quarters
A41: Report Date | B41: 45382 | C41: 45473 | D41: 45565 | E41: 45657 | F41: 45747 | G41: 45838 | H41: 45930 | I41: 46022 | J41: 46112 | K41: 46203
A42: Sales | B42: 12494 | C42: 13266 | D42: 14534 | E42: 17740 | F42: 14916 | G42: 16523 | H42: 18725 | I42: 25416 | J42: 26920 | K42: 21356
A43: Expenses | B43: 11303 | C43: 12019 | D43: 13298 | E43: 16066 | F43: 13379 | G43: 14693 | H43: 16850 | I43: 22703 | J43: 24982 | K43: 18466
A44: Other Income | B44: 159 | C44: 120 | D44: 123 | E44: 128 | F44: 116 | G44: 105 | H44: 113 | I44: -1 | J44: 235 | K44: 148
A45: Depreciation | B45: 158 | C45: 164 | D45: 171 | E45: 175 | F45: 183 | G45: 184 | H45: 189 | I45: 207 | J45: 246 | K45: 256
A46: Interest | B46: 201 | C46: 230 | D46: 240 | E46: 231 | F46: 252 | G46: 271 | H46: 277 | I46: 282 | J46: 350 | K46: 353
A47: Profit before tax | B47: 991 | C47: 973 | D47: 948 | E47: 1396 | F47: 1218 | G47: 1480 | H47: 1522 | I47: 2223 | J47: 1577 | K47: 2429
A48: Tax | B48: 220 | C48: 258 | D48: 244 | E48: 349 | F48: 347 | G48: 389 | H48: 402 | I48: 539 | J48: 398 | K48: 652
A49: Net profit | B49: 771 | C49: 715 | D49: 704 | E49: 1047 | F49: 871 | G49: 1091 | H49: 1120 | I49: 1684 | J49: 1179 | K49: 1777
A50: Operating Profit | B50: 1191 | C50: 1247 | D50: 1236 | E50: 1674 | F50: 1537 | G50: 1830 | H50: 1875 | I50: 2713 | J50: 1938 | K50: 2890
A55: BALANCE SHEET
A56: Report Date | B56: 42825 | C56: 43190 | D56: 43555 | E56: 43921 | F56: 44286 | G56: 44651 | H56: 45016 | I56: 45382 | J56: 45747 | K56: 46112
A57: Equity Share Capital | B57: 88.78 | C57: 88.78 | D57: 88.78 | E57: 89 | F57: 89 | G57: 89 | H57: 89 | I57: 89 | J57: 89 | K57: 89
A58: Reserves | B58: 4143.6 | C58: 5001.1 | D58: 5981.37 | E58: 6580 | F58: 7408 | G58: 9214 | H58: 11762 | I58: 9304 | J58: 11535 | K58: 15614
A59: Borrowings | B59: 1882.43 | C59: 1691.01 | D59: 2392.98 | E59: 3562 | F59: 5638 | G59: 7275 | H59: 9367 | I59: 15528 | J59: 20777 | K59: 30621
A60: Other Liabilities | B60: 2292.76 | C60: 2740.15 | D60: 3246.71 | E60: 3313 | F60: 3309 | G60: 4610 | H60: 5802 | I60: 6626 | J60: 8244 | K60: 14237
A61: Total | B61: 8407.57 | C61: 9521.04 | D61: 11709.84 | E61: 13544 | F61: 16444 | G61: 21188 | H61: 27020 | I61: 31547 | J61: 40645 | K61: 60561
A62: Net Block | B62: 1188.72 | C62: 1473.81 | D62: 1566.63 | E62: 2633 | F62: 2523 | G62: 2544 | H62: 2998 | I62: 3709 | J62: 4062 | K62: 6878
A63: Capital Work in Progress | B63: 152.07 | C63: 43.37 | D63: 31.77 | E63: 18 | F63: 32 | G63: 85 | H63: 144 | I63: 97 | J63: 105 | K63: 163
A64: Investments | B64: 430.73 | C64: 35.99 | D64: 108.42 | E64: 158 | F64: 2824 | G64: 294 | H64: 2515 | I64: 2345 | J64: 1988 | K64: 3506
A65: Other Assets | B65: 6636.05 | C65: 7967.87 | D65: 10003.02 | E65: 10735 | F65: 11065 | G65: 18265 | H65: 21363 | I65: 25396 | J65: 34490 | K65: 50014
A66: Total | B66: 8407.57 | C66: 9521.04 | D66: 11709.84 | E66: 13544 | F66: 16444 | G66: 21188 | H66: 27020 | I66: 31547 | J66: 40645 | K66: 60561
A67: Receivables | B67: 207.6 | C67: 295.69 | D67: 420.45 | E67: 312 | F67: 366 | G67: 565 | H67: 674 | I67: 1018 | J67: 1068 | K67: 916
... A70: No. of Equity Shares | B70: 887786160 | C70: 887786160 | D70: 887786160 | E70: 887786160 | F70: 887786160 | G70: 887786160 | H70: 890000000 | I70: 890000000 | J70: 890000000 | K70: 890000000
A71: New Bonus Shares
A72: Face value | B72: 1 | C72: 1 | D72: 1 | E72: 1 | F72: 1 | G72: 1 | H72: 1 | I72: 1 | J72: 1 | K72: 1
A80: CASH FLOW:
A81: Report Date | B81: 42825 | C81: 43190 | D81: 43555 | E81: 43921 | F81: 44286 | G81: 44651 | H81: 45016 | I81: 45382 | J81: 45747 | K81: 46112
A82: Cash from Operating Activity | B82: 1712.3 | C82: -51.12 | D82: 1242.92 | E82: -348 | F82: 4139 | G82: -724 | H82: 1370 | I82: 1695 | J82: -541 | K82: 5590
A83: Cash from Investing Activity | B83: -953.15 | C83: 97.62 | D83: -796.61 | E83: 235 | F83: -2799 | G83: 1165 | H83: -1814 | I83: -189 | J83: 546 | K83: -2965
A84: Cash from Financing Activity | B84: -165.6 | C84: -252.45 | D84: -488.83 | E84: -242 | F84: -1234 | G84: -403 | H84: 457 | I84: -1329 | J84: -7 | K84: -2159
A85: Net Cash Flow | B85: 593.55 | C85: -205.95 | D85: -42.52 | E85: -355 | F85: 106 | G85: 38 | H85: 13 | I85: 177 | J85: -2 | K85: 466
A90: PRICE: | B90: 462.75 | C90: 942.3 | D90: 1141.85 | E90: 933.7 | F90: 1558.05 | G90: 2536.15 | H90: 2514.9 | I90: 3801.8 | J90: 3063.35 | K90: 3951.4
A92: DERIVED:
A93: Adjusted Equity Shares in Cr | B93: 88.78 | C93: 88.78 | D93: 88.78 | E93: 88.78 | F93: 88.78 | G93: 88.78 | H93: 89 | I93: 89 | J93: 89 | K93: 89
B96: 42795 | C96: 43160 | D96: 43525 | E96: 43891 | F96: 44256 | G96: 44621 | H96: 44986 | I96: 45352 | J96: 45717 | K96: 46082
A97: Cash from Operating Activity - | B97: 1712 | C97: -51 | D97: 1243 | E97: -348 | F97: 4139 | G97: -724 | H97: 1370 | I97: 1695 | J97: -541 | K97: 5590
A98: Profit from operations | B98: 1073 | C98: 1642 | D98: 2183 | E98: 2481 | F98: 1789 | G98: 3298 | H98: 4937 | I98: 5404 | J98: 5774 | K98: 8447
A99: Receivables | B99: -12 | C99: -90 | D99: -139 | E99: 109 | F99: -59 | G99: -207 | H99: -112 | I99: -348 | J99: -95 | K99: 210
A100: Inventory | B100: -448 | C100: -996 | D100: -1120 | E100: -1057 | F100: -316 | G100: -5199 | H100: -2977 | I100: -2462 | J100: -9072 | K100: -11592
A101: Payables | B101: 238 | C101: 95 | D101: 32 | E101: -310 | F101: 195 | G101: 504 | H101: -89 | I101: 196 | J101: 564 | K101: 472
A102: Loans Advances | B102: 0 | C102: 3 | D102: -24 | E102: -20 | F102: -8 | G102: -3 | H102: -18 | I102: -21 | J102: 4 | K102: -8
A103: Operating borrowings | B103: 763 | C103: -270 | D103: 741 | E103: -768 | F103: 2625 | G103: 1188 | H103: -99 | I103: 42 | J103: 2468 | K103: 7304
A104: Other WC items | B104: 375 | C104: 22 | D104: 206 | E104: -226 | F104: 184 | G104: 497 | H104: 882 | I104: 57 | J104: 905 | K104: 2494
A105: Working capital changes | B105: 916 | C105: -1237 | D105: -304 | E105: -2272 | F105: 2621 | G105: -3220 | H105: -2413 | I105: -2536 | J105: -5226 | K105: -1120
A106: Direct taxes | B106: -277 | C106: -456 | D106: -636 | E106: -557 | F106: -271 | G106: -802 | H106: -1154 | I106: -1173 | J106: -1089 | K106: -1737
A107: Cash from Investing Activity - | B107: -953 | C107: 98 | D107: -797 | E107: 235 | F107: -2799 | G107: 1165 | H107: -1814 | I107: -189 | J107: 546 | K107: -2965
A108: Fixed assets purchased | B108: -256 | C108: -305 | D108: -265 | E108: -355 | F108: -146 | G108: -224 | H108: -432 | I108: -691 | J108: -494 | K108: -902
... A127: CFO/OP | B127: 1.71 | C127: 0.25 | D127: 0.94 | E127: 0.08 | F127: 2.56 | G127: 0.02 | H127: 0.52 | I127: 0.54 | J127: 0.1 | K127: 0.88
B129: FY 17 | C129: FY 18 | D129: FY 19 | E129: FY 20 | F129: FY 21 | G129: FY 22 | H129: FY 23 | I129: FY 24 | J129: FY 25 | K129: FY 26

Sheet Historical FS
B2: ="Historical Financial Statement -" & 'Data Sheet'!B1 -> Historical Financial Statement -TITAN COMPANY LTD
B3: Years | C3: ='Data Sheet'!B16 -> 42825 | D3: ='Data Sheet'!C16 -> 43190 | E3: ='Data Sheet'!D16 -> 43555 | F3: ='Data Sheet'!E16 -> 43921 | G3: ='Data Sheet'!F16 -> 44286 | H3: ='Data Sheet'!G16 -> 44651 | I3: ='Data Sheet'!H16 -> 45016 | J3: ='Data Sheet'!I16 -> 45382 | ... L3: ='Data Sheet'!K16 -> 46112 | M3: LTM
A4: # | B4: Income Statement
B5: Sales | C5: =IFERROR('Data Sheet'!B17, 0) -> 13260.83 | D5: =IFERROR('Data Sheet'!C17, 0) -> 16119.77 | E5: =IFERROR('Data Sheet'!D17, 0) -> 19778.52 | F5: =IFERROR('Data Sheet'!E17, 0) -> 21052 | G5: =IFERROR('Data Sheet'!F17, 0) -> 21644 | H5: =IFERROR('Data Sheet'!G17, 0) -> 28799 | I5: =IFERROR('Data Sheet'!H17, 0) -> 40575 | J5: =IFERROR('Data Sheet'!I17, 0) -> 51084 | ... L5: =IFERROR('Data Sheet'!K17, 0) -> 87584 | M5: =IFERROR(SUM('Data Sheet'!H42:K42),0) -> 92417
B6: Sales Growth | D6: =D5/C5-1 -> 0.21559284 | E6: =E5/D5-1 -> 0.22697284 | F6: =F5/E5-1 -> 0.064387022 | G6: =G5/F5-1 -> 0.028120844 | H6: =H5/G5-1 -> 0.3305766 | I6: =I5/H5-1 -> 0.40890309 | J6: =J5/I5-1 -> 0.25900185 | K6: =K5/J5-1 -> 0.18346253 | ... M6: =M5/L5-1 -> 0.055181312
B8: COGS | C8: =IFERROR(SUM('Data Sheet'!B18,'Data Sheet'!B20:B22)-1*'Data Sheet'!B19, 0) -> 10606.01 | D8: =IFERROR(SUM('Data Sheet'!C18,'Data Sheet'!C20:C22)-1*'Data Sheet'!C19, 0) -> 12762.63 | E8: =IFERROR(SUM('Data Sheet'!D18,'Data Sheet'!D20:D22)-1*'Data Sheet'!D19, 0) -> 15660.48 | F8: =IFERROR(SUM('Data Sheet'!E18,'Data Sheet'!E20:E22)-1*'Data Sheet'!E19, 0) -> 16626 | G8: =IFERROR(SUM('Data Sheet'!F18,'Data Sheet'!F20:F22)-1*'Data Sheet'!F19, 0) -> 17661 | H8: =IFERROR(SUM('Data Sheet'!G18,'Data Sheet'!G20:G22)-1*'Data Sheet'!G19, 0) -> 23225 | I8: =IFERROR(SUM('Data Sheet'!H18,'Data Sheet'!H20:H22)-1*'Data Sheet'!H19, 0) -> 32295 | J8: =IFERROR(SUM('Data Sheet'!I18,'Data Sheet'!I20:I22)-1*'Data Sheet'!I19, 0) -> 41664 | ... L8: =IFERROR(SUM('Data Sheet'!K18,'Data Sheet'!K20:K22)-1*'Data Sheet'!K19, 0) -> 73461 | M8: =IFERROR(SUM('Data Sheet'!H43:K43),0) -> 83001
B9: COGS % Sales | C9: =C8/C5 -> 0.79979986 | D9: =D8/D5 -> 0.79173772 | E9: =E8/E5 -> 0.79179231 | F9: =F8/F5 -> 0.78975869 | G9: =G8/G5 -> 0.81597671 | H9: =H8/H5 -> 0.80645161 | I9: =I8/I5 -> 0.79593346 | J9: =J8/J5 -> 0.81559784 | ... M9: =M8/M5 -> 0.89811398
B11: Gross Profit | C11: =C5-C8 -> 2654.82 | D11: =D5-D8 -> 3357.14 | E11: =E5-E8 -> 4118.04 | F11: =F5-F8 -> 4426 | G11: =G5-G8 -> 3983 | H11: =H5-H8 -> 5574 | I11: =I5-I8 -> 8280 | J11: =J5-J8 -> 9420 | ... M11: =M5-M8 -> 9416
B12: Gross Margin | C12: =C11/C5 -> 0.20020014 | D12: =D11/D5 -> 0.20826228 | E12: =E11/E5 -> 0.20820769 | F12: =F11/F5 -> 0.21024131 | G12: =G11/G5 -> 0.18402329 | H12: =H11/H5 -> 0.19354839 | I12: =I11/I5 -> 0.20406654 | J12: =J11/J5 -> 0.18440216 | ... M12: =M11/M5 -> 0.10188602
B14: Selling & General Expenses | C14: =IFERROR(SUM('Data Sheet'!B23,'Data Sheet'!B24),0) -> 1490.92 | D14: =IFERROR(SUM('Data Sheet'!C23,'Data Sheet'!C24),0) -> 1712.94 | E14: =IFERROR(SUM('Data Sheet'!D23,'Data Sheet'!D24),0) -> 2124.25 | F14: =IFERROR(SUM('Data Sheet'!E23,'Data Sheet'!E24),0) -> 1963 | G14: =IFERROR(SUM('Data Sheet'!F23,'Data Sheet'!F24),0) -> 2258 | H14: =IFERROR(SUM('Data Sheet'!G23,'Data Sheet'!G24),0) -> 2230 | I14: =IFERROR(SUM('Data Sheet'!H23,'Data Sheet'!H24),0) -> 3398 | J14: =IFERROR(SUM('Data Sheet'!I23,'Data Sheet'!I24),0) -> 4128 | ... L14: =IFERROR(SUM('Data Sheet'!K23,'Data Sheet'!K24),0) -> 5766
B15: S&G Exp %Sales | C15: =C14/C5 -> 0.11243037 | D15: =D14/D5 -> 0.1062633 | E15: =E14/E5 -> 0.10740187 | F15: =F14/F5 -> 0.093245297 | G15: =G14/G5 -> 0.10432452 | H15: =H14/H5 -> 0.077433244 | I15: =I14/I5 -> 0.083746149 | J15: =J14/J5 -> 0.080808081 | ... L15: =L14/L5 -> 0.065833942
B17: EBITDA | C17: =IFERROR('Historical FS'!C11-'Historical FS'!C14,0) -> 1163.9 | D17: =IFERROR('Historical FS'!D11-'Historical FS'!D14,0) -> 1644.2 | E17: =IFERROR('Historical FS'!E11-'Historical FS'!E14,0) -> 1993.79 | F17: =IFERROR('Historical FS'!F11-'Historical FS'!F14,0) -> 2463 | G17: =IFERROR('Historical FS'!G11-'Historical FS'!G14,0) -> 1725 | H17: =IFERROR('Historical FS'!H11-'Historical FS'!H14,0) -> 3344 | I17: =IFERROR('Historical FS'!I11-'Historical FS'!I14,0) -> 4882 | J17: =IFERROR('Historical FS'!J11-'Historical FS'!J14,0) -> 5292 | ... L17: =IFERROR('Historical FS'!L11-'Historical FS'!L14,0) -> 8357 | M17: =IFERROR(SUM('Data Sheet'!H50:K50),0) -> 9416
B18: EBITDA Margins | C18: =C17/C5 -> 0.08776977 | D18: =D17/D5 -> 0.10199897 | E18: =E17/E5 -> 0.10080582 | F18: =F17/F5 -> 0.11699601 | G18: =G17/G5 -> 0.079698762 | H18: =H17/H5 -> 0.11611514 | I18: =I17/I5 -> 0.12032039 | J18: =J17/J5 -> 0.10359408 | ... M18: =M17/M5 -> 0.10188602
B20: Depreciation | C20: =IFERROR('Data Sheet'!B26,0) -> 110.53 | D20: =IFERROR('Data Sheet'!C26,0) -> 131.43 | E20: =IFERROR('Data Sheet'!D26,0) -> 162.84 | F20: =IFERROR('Data Sheet'!E26,0) -> 348 | G20: =IFERROR('Data Sheet'!F26,0) -> 375 | H20: =IFERROR('Data Sheet'!G26,0) -> 399 | I20: =IFERROR('Data Sheet'!H26,0) -> 441 | J20: =IFERROR('Data Sheet'!I26,0) -> 584 | ... L20: =IFERROR('Data Sheet'!K26,0) -> 826 | M20: =IFERROR(SUM('Data Sheet'!H45:K45),0) -> 898
B21: Depreciation % Sales | C21: =C20/C5 -> 0.008335074 | D21: =D20/D5 -> 0.0081533421 | E21: =E20/E5 -> 0.0082331742 | F21: =F20/F5 -> 0.016530496 | G21: =G20/G5 -> 0.017325818 | H21: =H20/H5 -> 0.013854648 | I21: =I20/I5 -> 0.010868762 | J21: =J20/J5 -> 0.011432151 | ... M21: =M20/M5 -> 0.009716827
B23: EBIT | C23: =IFERROR(C17-C20,0) -> 1053.37 | D23: =IFERROR(D17-D20,0) -> 1512.77 | E23: =IFERROR(E17-E20,0) -> 1830.95 | F23: =IFERROR(F17-F20,0) -> 2115 | G23: =IFERROR(G17-G20,0) -> 1350 | H23: =IFERROR(H17-H20,0) -> 2945 | I23: =IFERROR(I17-I20,0) -> 4441 | J23: =IFERROR(J17-J20,0) -> 4708 | ... M23: =IFERROR(M17-M20,0) -> 8518
B24: EBIT %Sales | C24: =C23/C5 -> 0.079434696 | D24: =D23/D5 -> 0.093845632 | E24: =E23/E5 -> 0.09257265 | F24: =F23/F5 -> 0.10046551 | G24: =G23/G5 -> 0.062372944 | H24: =H23/H5 -> 0.1022605 | I24: =I23/I5 -> 0.10945163 | J24: =J23/J5 -> 0.092161929 | ... M24: =M23/M5 -> 0.09216919
B26: Other Income | C26: =IFERROR('Data Sheet'!B25,0) -> -42.38 | D26: =IFERROR('Data Sheet'!C25,0) -> 69.93 | E26: =IFERROR('Data Sheet'!D25,0) -> 178.48 | F26: =IFERROR('Data Sheet'!E25,0) -> 153 | G26: =IFERROR('Data Sheet'!F25,0) -> 180 | H26: =IFERROR('Data Sheet'!G25,0) -> 177 | I26: =IFERROR('Data Sheet'!H25,0) -> 306 | J26: =IFERROR('Data Sheet'!I25,0) -> 534 | ... L26: =IFERROR('Data Sheet'!K25,0) -> 450 | M26: =IFERROR(SUM('Data Sheet'!H44:K44),0) -> 495
B27: Other Income % Sales | C27: =C26/C5 -> -0.0031958784 | D27: =D26/D5 -> 0.0043381512 | E27: =E26/E5 -> 0.009023931 | F27: =F26/F5 -> 0.007267718 | G27: =G26/G5 -> 0.0083163925 | H27: =H26/H5 -> 0.0061460467 | I27: =I26/I5 -> 0.0075415896 | J27: =J26/J5 -> 0.010453371 | ... M27: =M26/M5 -> 0.0053561574
B29: Interest | C29: =IFERROR('Data Sheet'!B27,0) -> 37.74 | D29: =IFERROR('Data Sheet'!C27,0) -> 52.92 | E29: =IFERROR('Data Sheet'!D27,0) -> 52.54 | F29: =IFERROR('Data Sheet'!E27,0) -> 166 | G29: =IFERROR('Data Sheet'!F27,0) -> 203 | H29: =IFERROR('Data Sheet'!G27,0) -> 218 | I29: =IFERROR('Data Sheet'!H27,0) -> 300 | J29: =IFERROR('Data Sheet'!I27,0) -> 619 | ... L29: =IFERROR('Data Sheet'!K27,0) -> 1180 | M29: =IFERROR(SUM('Data Sheet'!H46:K46),0) -> 1262
B30: Interest % Sales | C30: =C29/C5 -> 0.0028459757 | D30: =D29/D5 -> 0.0032829253 | E30: =E29/E5 -> 0.0026564172 | F30: =F29/F5 -> 0.0078852366 | G30: =G29/G5 -> 0.0093790427 | H30: =H29/H5 -> 0.0075697073 | I30: =I29/I5 -> 0.0073937153 | J30: =J29/J5 -> 0.012117297 | ... M30: =M29/M5 -> 0.013655496
B32: PBT | C32: =C23+C26-C29 -> 973.25 | D32: =D23+D26-D29 -> 1529.78 | E32: =E23+E26-E29 -> 1956.89 | F32: =F23+F26-F29 -> 2102 | G32: =G23+G26-G29 -> 1327 | H32: =H23+H26-H29 -> 2904 | I32: =I23+I26-I29 -> 4447 | J32: =J23+J26-J29 -> 4623 | ... M32: =M23+M26-M29 -> 7751
B33: PBT % Sales | C33: =C32/C5 -> 0.073392842 | D33: =D32/D5 -> 0.094900858 | E33: =E32/E5 -> 0.098940163 | F33: =F32/F5 -> 0.099847995 | G33: =G32/G5 -> 0.061310294 | H33: =H32/H5 -> 0.10083683 | I33: =I32/I5 -> 0.10959951 | J33: =J32/J5 -> 0.090498003 | ... M33: =M32/M5 -> 0.083869851
B35: Tax | C35: =IFERROR('Data Sheet'!B29,0) -> 275.97 | D35: =IFERROR('Data Sheet'!C29,0) -> 427.87 | E35: =IFERROR('Data Sheet'!D29,0) -> 568.24 | F35: =IFERROR('Data Sheet'!E29,0) -> 609 | G35: =IFERROR('Data Sheet'!F29,0) -> 353 | H35: =IFERROR('Data Sheet'!G29,0) -> 706 | I35: =IFERROR('Data Sheet'!H29,0) -> 1173 | J35: =IFERROR('Data Sheet'!I29,0) -> 1127 | ... L35: =IFERROR('Data Sheet'!K29,0) -> 1728 | M35: =IFERROR(SUM('Data Sheet'!H48:K48),0) -> 1991
B36: Effective Tax Rate% | C36: =C35/C32 -> 0.2835551 | D36: =D35/D32 -> 0.27969381 | E36: =E35/E32 -> 0.29037912 | F36: =F35/F32 -> 0.28972407 | G36: =G35/G32 -> 0.26601356 | H36: =H35/H32 -> 0.24311295 | I36: =I35/I32 -> 0.26377333 | J36: =J35/J32 -> 0.24378109 | ... M36: =M35/M32 -> 0.25687008
B37: Other Adjustments | C37: =C39-(C32-C35) -> 14.19 | D37: =D39-(D32-D35) -> 28.18 | E37: =E39-(E32-E35) -> 15.5 | F37: =F39-(F32-F35) -> 8 | G37: =G39-(G32-G35) -> -1 | H37: =H39-(H32-H35) -> -25 | I37: =I39-(I32-I35) -> -24 | J37: =J39-(J32-J35) -> 0 | ... M37: =M39-(M32-M35) -> 0
B39: Net Profit | C39: =IFERROR('Data Sheet'!B30,0) -> 711.47 | D39: =IFERROR('Data Sheet'!C30,0) -> 1130.09 | E39: =IFERROR('Data Sheet'!D30,0) -> 1404.15 | F39: =IFERROR('Data Sheet'!E30,0) -> 1501 | G39: =IFERROR('Data Sheet'!F30,0) -> 973 | H39: =IFERROR('Data Sheet'!G30,0) -> 2173 | I39: =IFERROR('Data Sheet'!H30,0) -> 3250 | J39: =IFERROR('Data Sheet'!I30,0) -> 3496 | ... L39: =IFERROR('Data Sheet'!K30,0) -> 5073 | M39: =IFERROR(M32-M35,0) -> 5760
B40: Net Margins% | C40: =C39/C5 -> 0.053651996 | D40: =D39/D5 -> 0.070105839 | E40: =E39/E5 -> 0.070993684 | F40: =F39/F5 -> 0.071299639 | G40: =G39/G5 -> 0.044954722 | H40: =H39/H5 -> 0.075454009 | I40: =I39/I5 -> 0.080098583 | J40: =J39/J5 -> 0.068436301 | ... M40: =M39/M5 -> 0.062326195
B42: No. of Equity Shares | C42: =IFERROR('Data Sheet'!B93,0) -> 88.78 | D42: =IFERROR('Data Sheet'!C93,0) -> 88.78 | E42: =IFERROR('Data Sheet'!D93,0) -> 88.78 | F42: =IFERROR('Data Sheet'!E93,0) -> 88.78 | G42: =IFERROR('Data Sheet'!F93,0) -> 88.78 | H42: =IFERROR('Data Sheet'!G93,0) -> 88.78 | I42: =IFERROR('Data Sheet'!H93,0) -> 89 | J42: =IFERROR('Data Sheet'!I93,0) -> 89 | ... L42: =IFERROR('Data Sheet'!K93,0) -> 89 | M42: =IFERROR('Data Sheet'!K93,0) -> 89
B44: Earnings Per Share | C44: =C39/C42 -> 8.0138545 | D44: =D39/D42 -> 12.729106 | E44: =E39/E42 -> 15.816062 | F44: =F39/F42 -> 16.906961 | G44: =G39/G42 -> 10.959676 | H44: =H39/H42 -> 24.476233 | I44: =I39/I42 -> 36.516854 | J44: =J39/J42 -> 39.280899 | ... M44: =M39/M42 -> 64.719101
B45: EPS Growth % | D45: =D44/C44-1 -> 0.58838742 | E45: =E44/D44-1 -> 0.24251166 | F45: =F44/E44-1 -> 0.068974112 | G45: =G44/F44-1 -> -0.35176549 | H45: =H44/G44-1 -> 1.2332991 | I45: =I44/H44-1 -> 0.49193111 | J45: =J44/I44-1 -> 0.075692308 | K45: =K44/J44-1 -> -0.045480549 | ... M45: =M44/L44-1 -> 0.13542283
B47: Dividend Per Share | C47: =IFERROR('Data Sheet'!B31/'Historical FS'!C42,0) -> 2.6000225 | D47: =IFERROR('Data Sheet'!C31/'Historical FS'!D42,0) -> 3.7499437 | E47: =IFERROR('Data Sheet'!D31/'Historical FS'!E42,0) -> 5 | F47: =IFERROR('Data Sheet'!E31/'Historical FS'!F42,0) -> 4.0099121 | G47: =IFERROR('Data Sheet'!F31/'Historical FS'!G42,0) -> 4.0099121 | H47: =IFERROR('Data Sheet'!G31/'Historical FS'!H42,0) -> 7.5185853 | I47: =IFERROR('Data Sheet'!H31/'Historical FS'!I42,0) -> 10 | J47: =IFERROR('Data Sheet'!I31/'Historical FS'!J42,0) -> 11 | ... L47: =IFERROR('Data Sheet'!K31/'Historical FS'!L42,0) -> 15
B48: Dividend Payout Ratio | C48: =C47/C44 -> 0.32444095 | D48: =D47/D44 -> 0.29459601 | E48: =E47/E44 -> 0.31613432 | F48: =F47/F44 -> 0.23717522 | G48: =G47/G44 -> 0.36587873 | H48: =H47/H44 -> 0.30717902 | I48: =I47/I44 -> 0.27384615 | J48: =J47/J44 -> 0.28003432 | ... L48: =L47/L44 -> 0.26315789
B50: Retained Earnings | C50: =IFERROR(IF(C44>C47,1-C48,0),0) -> 0.67555905 | D50: =IFERROR(IF(D44>D47,1-D48,0),0) -> 0.70540399 | E50: =IFERROR(IF(E44>E47,1-E48,0),0) -> 0.68386568 | F50: =IFERROR(IF(F44>F47,1-F48,0),0) -> 0.76282478 | G50: =IFERROR(IF(G44>G47,1-G48,0),0) -> 0.63412127 | H50: =IFERROR(IF(H44>H47,1-H48,0),0) -> 0.69282098 | I50: =IFERROR(IF(I44>I47,1-I48,0),0) -> 0.72615385 | J50: =IFERROR(IF(J44>J47,1-J48,0),0) -> 0.71996568 | ... L50: =IFERROR(IF(L44>L47,1-L48,0),0) -> 0.73684211
A52: # | B52: Balance Sheet
B53: Equity Share Capital | C53: =IFERROR('Data Sheet'!B57,0) -> 88.78 | D53: =IFERROR('Data Sheet'!C57,0) -> 88.78 | E53: =IFERROR('Data Sheet'!D57,0) -> 88.78 | F53: =IFERROR('Data Sheet'!E57,0) -> 89 | G53: =IFERROR('Data Sheet'!F57,0) -> 89 | H53: =IFERROR('Data Sheet'!G57,0) -> 89 | I53: =IFERROR('Data Sheet'!H57,0) -> 89 | J53: =IFERROR('Data Sheet'!I57,0) -> 89 | ... L53: =IFERROR('Data Sheet'!K57,0) -> 89
B54: Reserves | C54: =IFERROR('Data Sheet'!B58,0) -> 4143.6 | D54: =IFERROR('Data Sheet'!C58,0) -> 5001.1 | E54: =IFERROR('Data Sheet'!D58,0) -> 5981.37 | F54: =IFERROR('Data Sheet'!E58,0) -> 6580 | G54: =IFERROR('Data Sheet'!F58,0) -> 7408 | H54: =IFERROR('Data Sheet'!G58,0) -> 9214 | I54: =IFERROR('Data Sheet'!H58,0) -> 11762 | J54: =IFERROR('Data Sheet'!I58,0) -> 9304 | ... L54: =IFERROR('Data Sheet'!K58,0) -> 15614
B55: Borrowings | C55: =IFERROR('Data Sheet'!B59,0) -> 1882.43 | D55: =IFERROR('Data Sheet'!C59,0) -> 1691.01 | E55: =IFERROR('Data Sheet'!D59,0) -> 2392.98 | F55: =IFERROR('Data Sheet'!E59,0) -> 3562 | G55: =IFERROR('Data Sheet'!F59,0) -> 5638 | H55: =IFERROR('Data Sheet'!G59,0) -> 7275 | I55: =IFERROR('Data Sheet'!H59,0) -> 9367 | J55: =IFERROR('Data Sheet'!I59,0) -> 15528 | ... L55: =IFERROR('Data Sheet'!K59,0) -> 30621
B56: Other Liabilities | C56: =IFERROR('Data Sheet'!B60,0) -> 2292.76 | D56: =IFERROR('Data Sheet'!C60,0) -> 2740.15 | E56: =IFERROR('Data Sheet'!D60,0) -> 3246.71 | F56: =IFERROR('Data Sheet'!E60,0) -> 3313 | G56: =IFERROR('Data Sheet'!F60,0) -> 3309 | H56: =IFERROR('Data Sheet'!G60,0) -> 4610 | I56: =IFERROR('Data Sheet'!H60,0) -> 5802 | J56: =IFERROR('Data Sheet'!I60,0) -> 6626 | ... L56: =IFERROR('Data Sheet'!K60,0) -> 14237
B57: Total Liabilities | C57: =IFERROR(SUM(C53:C56),0) -> 8407.57 | D57: =IFERROR(SUM(D53:D56),0) -> 9521.04 | E57: =IFERROR(SUM(E53:E56),0) -> 11709.84 | F57: =IFERROR(SUM(F53:F56),0) -> 13544 | G57: =IFERROR(SUM(G53:G56),0) -> 16444 | H57: =IFERROR(SUM(H53:H56),0) -> 21188 | I57: =IFERROR(SUM(I53:I56),0) -> 27020 | J57: =IFERROR(SUM(J53:J56),0) -> 31547 | ... L57: =IFERROR(SUM(L53:L56),0) -> 60561
B59: Net Block | C59: =IFERROR('Data Sheet'!B62,0) -> 1188.72 | D59: =IFERROR('Data Sheet'!C62,0) -> 1473.81 | E59: =IFERROR('Data Sheet'!D62,0) -> 1566.63 | F59: =IFERROR('Data Sheet'!E62,0) -> 2633 | G59: =IFERROR('Data Sheet'!F62,0) -> 2523 | H59: =IFERROR('Data Sheet'!G62,0) -> 2544 | I59: =IFERROR('Data Sheet'!H62,0) -> 2998 | J59: =IFERROR('Data Sheet'!I62,0) -> 3709 | ... L59: =IFERROR('Data Sheet'!K62,0) -> 6878
B60: Capital Work in Progress | C60: =IFERROR('Data Sheet'!B63,0) -> 152.07 | D60: =IFERROR('Data Sheet'!C63,0) -> 43.37 | E60: =IFERROR('Data Sheet'!D63,0) -> 31.77 | F60: =IFERROR('Data Sheet'!E63,0) -> 18 | G60: =IFERROR('Data Sheet'!F63,0) -> 32 | H60: =IFERROR('Data Sheet'!G63,0) -> 85 | I60: =IFERROR('Data Sheet'!H63,0) -> 144 | J60: =IFERROR('Data Sheet'!I63,0) -> 97 | ... L60: =IFERROR('Data Sheet'!K63,0) -> 163
B61: Investments | C61: =IFERROR('Data Sheet'!B64,0) -> 430.73 | D61: =IFERROR('Data Sheet'!C64,0) -> 35.99 | E61: =IFERROR('Data Sheet'!D64,0) -> 108.42 | F61: =IFERROR('Data Sheet'!E64,0) -> 158 | G61: =IFERROR('Data Sheet'!F64,0) -> 2824 | H61: =IFERROR('Data Sheet'!G64,0) -> 294 | I61: =IFERROR('Data Sheet'!H64,0) -> 2515 | J61: =IFERROR('Data Sheet'!I64,0) -> 2345 | ... L61: =IFERROR('Data Sheet'!K64,0) -> 3506
B62: Other Assets | C62: =IFERROR('Data Sheet'!B65-SUM('Data Sheet'!B67:B69),0) -> 723.78 | D62: =IFERROR('Data Sheet'!C65-SUM('Data Sheet'!C67:C69),0) -> 1129.43 | E62: =IFERROR('Data Sheet'!D65-SUM('Data Sheet'!D67:D69),0) -> 1477.27 | F62: =IFERROR('Data Sheet'!E65-SUM('Data Sheet'!E67:E69),0) -> 1939 | G62: =IFERROR('Data Sheet'!F65-SUM('Data Sheet'!F67:F69),0) -> 1731 | H62: =IFERROR('Data Sheet'!G65-SUM('Data Sheet'!G67:G69),0) -> 2518 | I62: =IFERROR('Data Sheet'!H65-SUM('Data Sheet'!H67:H69),0) -> 2762 | J62: =IFERROR('Data Sheet'!I65-SUM('Data Sheet'!I67:I69),0) -> 3801 | ... L62: =IFERROR('Data Sheet'!K65-SUM('Data Sheet'!K67:K69),0) -> 4438
B63: Total Non Current Assets | C63: =IFERROR(SUM(C59:C62),0) -> 2495.3 | D63: =IFERROR(SUM(D59:D62),0) -> 2682.6 | E63: =IFERROR(SUM(E59:E62),0) -> 3184.09 | F63: =IFERROR(SUM(F59:F62),0) -> 4748 | G63: =IFERROR(SUM(G59:G62),0) -> 7110 | H63: =IFERROR(SUM(H59:H62),0) -> 5441 | I63: =IFERROR(SUM(I59:I62),0) -> 8419 | J63: =IFERROR(SUM(J59:J62),0) -> 9952 | ... L63: =IFERROR(SUM(L59:L62),0) -> 14985
B65: Receivables | C65: =IFERROR('Data Sheet'!B67,0) -> 207.6 | D65: =IFERROR('Data Sheet'!C67,0) -> 295.69 | E65: =IFERROR('Data Sheet'!D67,0) -> 420.45 | F65: =IFERROR('Data Sheet'!E67,0) -> 312 | G65: =IFERROR('Data Sheet'!F67,0) -> 366 | H65: =IFERROR('Data Sheet'!G67,0) -> 565 | I65: =IFERROR('Data Sheet'!H67,0) -> 674 | J65: =IFERROR('Data Sheet'!I67,0) -> 1018 | ... L65: =IFERROR('Data Sheet'!K67,0) -> 916
B66: Inventory | C66: =IFERROR('Data Sheet'!B68,0) -> 4925.74 | D66: =IFERROR('Data Sheet'!C68,0) -> 5924.84 | E66: =IFERROR('Data Sheet'!D68,0) -> 7038.82 | F66: =IFERROR('Data Sheet'!E68,0) -> 8103 | G66: =IFERROR('Data Sheet'!F68,0) -> 8408 | H66: =IFERROR('Data Sheet'!G68,0) -> 13609 | I66: =IFERROR('Data Sheet'!H68,0) -> 16584 | J66: =IFERROR('Data Sheet'!I68,0) -> 19051 | ... L66: =IFERROR('Data Sheet'!K68,0) -> 42743
B67: Cash & Bank | C67: =IFERROR('Data Sheet'!B69,0) -> 778.93 | D67: =IFERROR('Data Sheet'!C69,0) -> 617.91 | E67: =IFERROR('Data Sheet'!D69,0) -> 1066.48 | F67: =IFERROR('Data Sheet'!E69,0) -> 381 | G67: =IFERROR('Data Sheet'!F69,0) -> 560 | H67: =IFERROR('Data Sheet'!G69,0) -> 1573 | I67: =IFERROR('Data Sheet'!H69,0) -> 1343 | J67: =IFERROR('Data Sheet'!I69,0) -> 1526 | ... L67: =IFERROR('Data Sheet'!K69,0) -> 1917
B68: Total Current Assets | C68: =IFERROR(SUM(C65:C67),0) -> 5912.27 | D68: =IFERROR(SUM(D65:D67),0) -> 6838.44 | E68: =IFERROR(SUM(E65:E67),0) -> 8525.75 | F68: =IFERROR(SUM(F65:F67),0) -> 8796 | G68: =IFERROR(SUM(G65:G67),0) -> 9334 | H68: =IFERROR(SUM(H65:H67),0) -> 15747 | I68: =IFERROR(SUM(I65:I67),0) -> 18601 | J68: =IFERROR(SUM(J65:J67),0) -> 21595 | ... L68: =IFERROR(SUM(L65:L67),0) -> 45576
B70: Total Assets | C70: =IFERROR(C68+C63,0) -> 8407.57 | D70: =IFERROR(D68+D63,0) -> 9521.04 | E70: =IFERROR(E68+E63,0) -> 11709.84 | F70: =IFERROR(F68+F63,0) -> 13544 | G70: =IFERROR(G68+G63,0) -> 16444 | H70: =IFERROR(H68+H63,0) -> 21188 | I70: =IFERROR(I68+I63,0) -> 27020 | J70: =IFERROR(J68+J63,0) -> 31547 | ... L70: =IFERROR(L68+L63,0) -> 60561
B72: Check | C72: =C70=C57 -> TRUE | D72: =D70=D57 -> TRUE | E72: =E70=E57 -> TRUE | F72: =F70=F57 -> TRUE | G72: =G70=G57 -> TRUE | H72: =H70=H57 -> TRUE | I72: =I70=I57 -> TRUE | J72: =J70=J57 -> TRUE | ... L72: =L70=L57 -> TRUE
A74: # | B74: Cash Flow Statement
B75: Operating Activity
B76: Profit from operations | C76: =IFERROR('Data Sheet'!B98,0) -> 1073 | D76: =IFERROR('Data Sheet'!C98,0) -> 1642 | E76: =IFERROR('Data Sheet'!D98,0) -> 2183 | F76: =IFERROR('Data Sheet'!E98,0) -> 2481 | G76: =IFERROR('Data Sheet'!F98,0) -> 1789 | H76: =IFERROR('Data Sheet'!G98,0) -> 3298 | I76: =IFERROR('Data Sheet'!H98,0) -> 4937 | J76: =IFERROR('Data Sheet'!I98,0) -> 5404 | ... L76: =IFERROR('Data Sheet'!K98,0) -> 8447
B77: Receivables | C77: =IFERROR('Data Sheet'!B99,0) -> -12 | D77: =IFERROR('Data Sheet'!C99,0) -> -90 | E77: =IFERROR('Data Sheet'!D99,0) -> -139 | F77: =IFERROR('Data Sheet'!E99,0) -> 109 | G77: =IFERROR('Data Sheet'!F99,0) -> -59 | H77: =IFERROR('Data Sheet'!G99,0) -> -207 | I77: =IFERROR('Data Sheet'!H99,0) -> -112 | J77: =IFERROR('Data Sheet'!I99,0) -> -348 | ... L77: =IFERROR('Data Sheet'!K99,0) -> 210
B78: Inventory | C78: =IFERROR('Data Sheet'!B100,0) -> -448 | D78: =IFERROR('Data Sheet'!C100,0) -> -996 | E78: =IFERROR('Data Sheet'!D100,0) -> -1120 | F78: =IFERROR('Data Sheet'!E100,0) -> -1057 | G78: =IFERROR('Data Sheet'!F100,0) -> -316 | H78: =IFERROR('Data Sheet'!G100,0) -> -5199 | I78: =IFERROR('Data Sheet'!H100,0) -> -2977 | J78: =IFERROR('Data Sheet'!I100,0) -> -2462 | ... L78: =IFERROR('Data Sheet'!K100,0) -> -11592
B79: Payables | C79: =IFERROR('Data Sheet'!B101,0) -> 238 | D79: =IFERROR('Data Sheet'!C101,0) -> 95 | E79: =IFERROR('Data Sheet'!D101,0) -> 32 | F79: =IFERROR('Data Sheet'!E101,0) -> -310 | G79: =IFERROR('Data Sheet'!F101,0) -> 195 | H79: =IFERROR('Data Sheet'!G101,0) -> 504 | I79: =IFERROR('Data Sheet'!H101,0) -> -89 | J79: =IFERROR('Data Sheet'!I101,0) -> 196 | ... L79: =IFERROR('Data Sheet'!K101,0) -> 472
B80: Loans Advances | C80: =IFERROR('Data Sheet'!B102,0) -> 0 | D80: =IFERROR('Data Sheet'!C102,0) -> 3 | E80: =IFERROR('Data Sheet'!D102,0) -> -24 | F80: =IFERROR('Data Sheet'!E102,0) -> -20 | G80: =IFERROR('Data Sheet'!F102,0) -> -8 | H80: =IFERROR('Data Sheet'!G102,0) -> -3 | I80: =IFERROR('Data Sheet'!H102,0) -> -18 | J80: =IFERROR('Data Sheet'!I102,0) -> -21 | ... L80: =IFERROR('Data Sheet'!K102,0) -> -8
B81: Operating borrowings | C81: =IFERROR('Data Sheet'!B103,0) -> 763 | D81: =IFERROR('Data Sheet'!C103,0) -> -270 | E81: =IFERROR('Data Sheet'!D103,0) -> 741 | F81: =IFERROR('Data Sheet'!E103,0) -> -768 | G81: =IFERROR('Data Sheet'!F103,0) -> 2625 | H81: =IFERROR('Data Sheet'!G103,0) -> 1188 | I81: =IFERROR('Data Sheet'!H103,0) -> -99 | J81: =IFERROR('Data Sheet'!I103,0) -> 42 | ... L81: =IFERROR('Data Sheet'!K103,0) -> 7304
B82: Other WC items | C82: =IFERROR('Data Sheet'!B104,0) -> 375 | D82: =IFERROR('Data Sheet'!C104,0) -> 22 | E82: =IFERROR('Data Sheet'!D104,0) -> 206 | F82: =IFERROR('Data Sheet'!E104,0) -> -226 | G82: =IFERROR('Data Sheet'!F104,0) -> 184 | H82: =IFERROR('Data Sheet'!G104,0) -> 497 | I82: =IFERROR('Data Sheet'!H104,0) -> 882 | J82: =IFERROR('Data Sheet'!I104,0) -> 57 | ... L82: =IFERROR('Data Sheet'!K104,0) -> 2494
B83: Working capital changes | C83: =IFERROR('Data Sheet'!B105,0) -> 916 | D83: =IFERROR('Data Sheet'!C105,0) -> -1237 | E83: =IFERROR('Data Sheet'!D105,0) -> -304 | F83: =IFERROR('Data Sheet'!E105,0) -> -2272 | G83: =IFERROR('Data Sheet'!F105,0) -> 2621 | H83: =IFERROR('Data Sheet'!G105,0) -> -3220 | I83: =IFERROR('Data Sheet'!H105,0) -> -2413 | J83: =IFERROR('Data Sheet'!I105,0) -> -2536 | ... L83: =IFERROR('Data Sheet'!K105,0) -> -1120
B84: Direct taxes | C84: =IFERROR('Data Sheet'!B106,0) -> -277 | D84: =IFERROR('Data Sheet'!C106,0) -> -456 | E84: =IFERROR('Data Sheet'!D106,0) -> -636 | F84: =IFERROR('Data Sheet'!E106,0) -> -557 | G84: =IFERROR('Data Sheet'!F106,0) -> -271 | H84: =IFERROR('Data Sheet'!G106,0) -> -802 | I84: =IFERROR('Data Sheet'!H106,0) -> -1154 | J84: =IFERROR('Data Sheet'!I106,0) -> -1173 | ... L84: =IFERROR('Data Sheet'!K106,0) -> -1737
B85: Cash From Operating Activity | C85: =SUM(C76:C82,C84) -> 1712 | D85: =SUM(D76:D82,D84) -> -50 | E85: =SUM(E76:E82,E84) -> 1243 | F85: =SUM(F76:F82,F84) -> -348 | G85: =SUM(G76:G82,G84) -> 4139 | H85: =SUM(H76:H82,H84) -> -724 | I85: =SUM(I76:I82,I84) -> 1370 | J85: =SUM(J76:J82,J84) -> 1695 | ... L85: =SUM(L76:L82,L84) -> 5590
B87: Investing Activity
B88: Fixed assets purchased | C88: =IFERROR('Data Sheet'!B108,0) -> -256 | D88: =IFERROR('Data Sheet'!C108,0) -> -305 | E88: =IFERROR('Data Sheet'!D108,0) -> -265 | F88: =IFERROR('Data Sheet'!E108,0) -> -355 | G88: =IFERROR('Data Sheet'!F108,0) -> -146 | H88: =IFERROR('Data Sheet'!G108,0) -> -224 | I88: =IFERROR('Data Sheet'!H108,0) -> -432 | J88: =IFERROR('Data Sheet'!I108,0) -> -691 | ... L88: =IFERROR('Data Sheet'!K108,0) -> -902
B89: Fixed assets sold | C89: =IFERROR('Data Sheet'!B109,0) -> 5 | D89: =IFERROR('Data Sheet'!C109,0) -> 6 | E89: =IFERROR('Data Sheet'!D109,0) -> 1 | F89: =IFERROR('Data Sheet'!E109,0) -> 10 | G89: =IFERROR('Data Sheet'!F109,0) -> 7 | H89: =IFERROR('Data Sheet'!G109,0) -> 8 | I89: =IFERROR('Data Sheet'!H109,0) -> 12 | J89: =IFERROR('Data Sheet'!I109,0) -> 20 | ... L89: =IFERROR('Data Sheet'!K109,0) -> 25
B90: Investments purchased | C90: =IFERROR('Data Sheet'!B110,0) -> -325 | D90: =IFERROR('Data Sheet'!C110,0) -> 0 | E90: =IFERROR('Data Sheet'!D110,0) -> -36 | F90: =IFERROR('Data Sheet'!E110,0) -> -13 | G90: =IFERROR('Data Sheet'!F110,0) -> -2656 | H90: =IFERROR('Data Sheet'!G110,0) -> -253 | I90: =IFERROR('Data Sheet'!H110,0) -> -2104 | J90: =IFERROR('Data Sheet'!I110,0) -> -21893 | ... L90: =IFERROR('Data Sheet'!K110,0) -> -22035
B91: Investments sold | C91: =IFERROR('Data Sheet'!B111,0) -> 0 | D91: =IFERROR('Data Sheet'!C111,0) -> 412 | E91: =IFERROR('Data Sheet'!D111,0) -> 18 | F91: =IFERROR('Data Sheet'!E111,0) -> 0 | G91: =IFERROR('Data Sheet'!F111,0) -> 43 | H91: =IFERROR('Data Sheet'!G111,0) -> 2870 | I91: =IFERROR('Data Sheet'!H111,0) -> 0 | J91: =IFERROR('Data Sheet'!I111,0) -> 22213 | ... L91: =IFERROR('Data Sheet'!K111,0) -> 20797
B92: Interest received | C92: =IFERROR('Data Sheet'!B112,0) -> 41 | D92: =IFERROR('Data Sheet'!C112,0) -> 64 | E92: =IFERROR('Data Sheet'!D112,0) -> 85 | F92: =IFERROR('Data Sheet'!E112,0) -> 73 | G92: =IFERROR('Data Sheet'!F112,0) -> 49 | H92: =IFERROR('Data Sheet'!G112,0) -> 56 | I92: =IFERROR('Data Sheet'!H112,0) -> 143 | J92: =IFERROR('Data Sheet'!I112,0) -> 249 | ... L92: =IFERROR('Data Sheet'!K112,0) -> 227
B93: Invest in subsidiaries | C93: =IFERROR('Data Sheet'!B113,0) -> 0 | D93: =IFERROR('Data Sheet'!C113,0) -> 0 | E93: =IFERROR('Data Sheet'!D113,0) -> 0 | F93: =IFERROR('Data Sheet'!E113,0) -> -39 | G93: =IFERROR('Data Sheet'!F113,0) -> 0 | H93: =IFERROR('Data Sheet'!G113,0) -> 0 | I93: =IFERROR('Data Sheet'!H113,0) -> 0 | J93: =IFERROR('Data Sheet'!I113,0) -> 0 | ... L93: =IFERROR('Data Sheet'!K113,0) -> 0
B94: Investment in group cos | C94: =IFERROR('Data Sheet'!B114,0) -> 0 | D94: =IFERROR('Data Sheet'!C114,0) -> 0 | E94: =IFERROR('Data Sheet'!D114,0) -> 0 | F94: =IFERROR('Data Sheet'!E114,0) -> 0 | G94: =IFERROR('Data Sheet'!F114,0) -> 0 | H94: =IFERROR('Data Sheet'!G114,0) -> 0 | I94: =IFERROR('Data Sheet'!H114,0) -> 0 | J94: =IFERROR('Data Sheet'!I114,0) -> 0 | ... L94: =IFERROR('Data Sheet'!K114,0) -> 0
B95: Acquisition of companies | C95: =IFERROR('Data Sheet'!B115,0) -> -385 | D95: =IFERROR('Data Sheet'!C115,0) -> 0 | E95: =IFERROR('Data Sheet'!D115,0) -> 0 | F95: =IFERROR('Data Sheet'!E115,0) -> 0 | G95: =IFERROR('Data Sheet'!F115,0) -> 0 | H95: =IFERROR('Data Sheet'!G115,0) -> 0 | I95: =IFERROR('Data Sheet'!H115,0) -> 0 | J95: =IFERROR('Data Sheet'!I115,0) -> 0 | ... L95: =IFERROR('Data Sheet'!K115,0) -> 0
B96: Inter corporate deposits | C96: =IFERROR('Data Sheet'!B116,0) -> 5 | D96: =IFERROR('Data Sheet'!C116,0) -> -35 | E96: =IFERROR('Data Sheet'!D116,0) -> -115 | F96: =IFERROR('Data Sheet'!E116,0) -> 200 | G96: =IFERROR('Data Sheet'!F116,0) -> -50 | H96: =IFERROR('Data Sheet'!G116,0) -> -344 | I96: =IFERROR('Data Sheet'!H116,0) -> 294 | J96: =IFERROR('Data Sheet'!I116,0) -> -143 | ... L96: =IFERROR('Data Sheet'!K116,0) -> 0
B97: Other investing items | C97: =IFERROR('Data Sheet'!B117,0) -> -38 | D97: =IFERROR('Data Sheet'!C117,0) -> -43 | E97: =IFERROR('Data Sheet'!D117,0) -> -485 | F97: =IFERROR('Data Sheet'!E117,0) -> 359 | G97: =IFERROR('Data Sheet'!F117,0) -> -46 | H97: =IFERROR('Data Sheet'!G117,0) -> -948 | I97: =IFERROR('Data Sheet'!H117,0) -> 273 | J97: =IFERROR('Data Sheet'!I117,0) -> 56 | ... L97: =IFERROR('Data Sheet'!K117,0) -> -1077
B98: Cash from Investing Activity - | C98: =SUM(C88:C97) -> -953 | D98: =SUM(D88:D97) -> 99 | E98: =SUM(E88:E97) -> -797 | F98: =SUM(F88:F97) -> 235 | G98: =SUM(G88:G97) -> -2799 | H98: =SUM(H88:H97) -> 1165 | I98: =SUM(I88:I97) -> -1814 | J98: =SUM(J88:J97) -> -189 | ... L98: =SUM(L88:L97) -> -2965
B100: Financing Activity
B101: Proceeds from borrowings | C101: =IFERROR('Data Sheet'!B119,0) -> 0 | D101: =IFERROR('Data Sheet'!C119,0) -> 0 | E101: =IFERROR('Data Sheet'!D119,0) -> 0 | F101: =IFERROR('Data Sheet'!E119,0) -> 693 | G101: =IFERROR('Data Sheet'!F119,0) -> 0 | H101: =IFERROR('Data Sheet'!G119,0) -> 349 | I101: =IFERROR('Data Sheet'!H119,0) -> 1684 | J101: =IFERROR('Data Sheet'!I119,0) -> 5629 | ... L101: =IFERROR('Data Sheet'!K119,0) -> 3314
B102: Repayment of borrowings | C102: =IFERROR('Data Sheet'!B120,0) -> 0 | D102: =IFERROR('Data Sheet'!C120,0) -> 0 | E102: =IFERROR('Data Sheet'!D120,0) -> -39 | F102: =IFERROR('Data Sheet'!E120,0) -> 0 | G102: =IFERROR('Data Sheet'!F120,0) -> -562 | H102: =IFERROR('Data Sheet'!G120,0) -> -7 | I102: =IFERROR('Data Sheet'!H120,0) -> -7 | J102: =IFERROR('Data Sheet'!I120,0) -> 0 | ... L102: =IFERROR('Data Sheet'!K120,0) -> -2632
B103: Interest paid fin | C103: =IFERROR('Data Sheet'!B121,0) -> -38 | D103: =IFERROR('Data Sheet'!C121,0) -> -54 | E103: =IFERROR('Data Sheet'!D121,0) -> -53 | F103: =IFERROR('Data Sheet'!E121,0) -> -399 | G103: =IFERROR('Data Sheet'!F121,0) -> -317 | H103: =IFERROR('Data Sheet'!G121,0) -> -218 | I103: =IFERROR('Data Sheet'!H121,0) -> -300 | J103: =IFERROR('Data Sheet'!I121,0) -> -619 | ... L103: =IFERROR('Data Sheet'!K121,0) -> -1000
B104: Dividends paid | C104: =IFERROR('Data Sheet'!B122,0) -> -4 | D104: =IFERROR('Data Sheet'!C122,0) -> -277 | E104: =IFERROR('Data Sheet'!D122,0) -> -397 | F104: =IFERROR('Data Sheet'!E122,0) -> -536 | G104: =IFERROR('Data Sheet'!F122,0) -> -355 | H104: =IFERROR('Data Sheet'!G122,0) -> -355 | I104: =IFERROR('Data Sheet'!H122,0) -> -666 | J104: =IFERROR('Data Sheet'!I122,0) -> -888 | ... L104: =IFERROR('Data Sheet'!K122,0) -> -976
B105: Financial liabilities | C105: =IFERROR('Data Sheet'!B123,0) -> 0 | D105: =IFERROR('Data Sheet'!C123,0) -> 0 | E105: =IFERROR('Data Sheet'!D123,0) -> 0 | F105: =IFERROR('Data Sheet'!E123,0) -> 0 | G105: =IFERROR('Data Sheet'!F123,0) -> 0 | H105: =IFERROR('Data Sheet'!G123,0) -> -172 | I105: =IFERROR('Data Sheet'!H123,0) -> -254 | J105: =IFERROR('Data Sheet'!I123,0) -> -318 | ... L105: =IFERROR('Data Sheet'!K123,0) -> -865
B106: Other financing items | C106: =IFERROR('Data Sheet'!B124,0) -> -124 | D106: =IFERROR('Data Sheet'!C124,0) -> 79 | E106: =IFERROR('Data Sheet'!D124,0) -> 0 | F106: =IFERROR('Data Sheet'!E124,0) -> 0 | G106: =IFERROR('Data Sheet'!F124,0) -> 0 | H106: =IFERROR('Data Sheet'!G124,0) -> 0 | I106: =IFERROR('Data Sheet'!H124,0) -> 0 | J106: =IFERROR('Data Sheet'!I124,0) -> -5133 | ... L106: =IFERROR('Data Sheet'!K124,0) -> 0
B107: Cash from Financing Activity | C107: =SUM(C101:C106) -> -166 | D107: =SUM(D101:D106) -> -252 | E107: =SUM(E101:E106) -> -489 | F107: =SUM(F101:F106) -> -242 | G107: =SUM(G101:G106) -> -1234 | H107: =SUM(H101:H106) -> -403 | I107: =SUM(I101:I106) -> 457 | J107: =SUM(J101:J106) -> -1329 | ... L107: =SUM(L101:L106) -> -2159
B109: Net Cashflow | C109: =IFERROR(C85+C98+C107,0) -> 593 | D109: =IFERROR(D85+D98+D107,0) -> -203 | E109: =IFERROR(E85+E98+E107,0) -> -43 | F109: =IFERROR(F85+F98+F107,0) -> -355 | G109: =IFERROR(G85+G98+G107,0) -> 106 | H109: =IFERROR(H85+H98+H107,0) -> 38 | I109: =IFERROR(I85+I98+I107,0) -> 13 | J109: =IFERROR(J85+J98+J107,0) -> 177 | ... L109: =IFERROR(L85+L98+L107,0) -> 466
B112: Supplementary data (consolidated, from annual report)
B114: Trade Payables | C114: 783 | D114: 878 | E114: 906 | F114: 596 | G114: 789 | H114: 1294 | I114: 1214 | J114: 1410 | K114: 1963 | L114: 2864

Sheet Ratio Analysis
B2: ="Ratio Analysis -" & 'Data Sheet'!B1 -> Ratio Analysis -TITAN COMPANY LTD
B3: Years | C3: ='Data Sheet'!B16 -> 42825 | D3: ='Data Sheet'!C16 -> 43190 | E3: ='Data Sheet'!D16 -> 43555 | F3: ='Data Sheet'!E16 -> 43921 | G3: ='Data Sheet'!F16 -> 44286 | H3: ='Data Sheet'!G16 -> 44651 | I3: ='Data Sheet'!H16 -> 45016 | J3: ='Data Sheet'!I16 -> 45382 | ... L3: ='Data Sheet'!K16 -> 46112 | M3: Trend | N3: Mean | O3: Median
B5: Sales Growth | D5: =IFERROR('Historical FS'!D6,0) -> 0.21559284 | E5: =IFERROR('Historical FS'!E6,0) -> 0.22697284 | F5: =IFERROR('Historical FS'!F6,0) -> 0.064387022 | G5: =IFERROR('Historical FS'!G6,0) -> 0.028120844 | H5: =IFERROR('Historical FS'!H6,0) -> 0.3305766 | I5: =IFERROR('Historical FS'!I6,0) -> 0.40890309 | J5: =IFERROR('Historical FS'!J6,0) -> 0.25900185 | K5: =IFERROR('Historical FS'!K6,0) -> 0.18346253 | L5: =IFERROR('Historical FS'!L6,0) -> 0.44872304 | N5: =IFERROR(AVERAGE(D5:L5),0) -> 0.24063785 | O5: =IFERROR(MEDIAN(D5:L5),0) -> 0.22697284
B6: EBITDA Growth | D6: =IFERROR('Historical FS'!D17/'Historical FS'!C17-1,0) -> 0.41266432 | E6: =IFERROR('Historical FS'!E17/'Historical FS'!D17-1,0) -> 0.21262012 | F6: =IFERROR('Historical FS'!F17/'Historical FS'!E17-1,0) -> 0.23533572 | G6: =IFERROR('Historical FS'!G17/'Historical FS'!F17-1,0) -> -0.29963459 | H6: =IFERROR('Historical FS'!H17/'Historical FS'!G17-1,0) -> 0.93855072 | I6: =IFERROR('Historical FS'!I17/'Historical FS'!H17-1,0) -> 0.45992823 | J6: =IFERROR('Historical FS'!J17/'Historical FS'!I17-1,0) -> 0.083981975 | K6: =IFERROR('Historical FS'!K17/'Historical FS'!J17-1,0) -> 0.075963719 | L6: =IFERROR('Historical FS'!L17/'Historical FS'!K17-1,0) -> 0.46768528 | N6: =IFERROR(AVERAGE(D6:L6),0) -> 0.28745505 | O6: =IFERROR(MEDIAN(D6:L6),0) -> 0.23533572
B7: EBIT Growth | D7: =IFERROR('Historical FS'!D23/'Historical FS'!C23-1,0) -> 0.43612406 | E7: =IFERROR('Historical FS'!E23/'Historical FS'!D23-1,0) -> 0.2103294 | F7: =IFERROR('Historical FS'!F23/'Historical FS'!E23-1,0) -> 0.15513804 | G7: =IFERROR('Historical FS'!G23/'Historical FS'!F23-1,0) -> -0.36170213 | H7: =IFERROR('Historical FS'!H23/'Historical FS'!G23-1,0) -> 1.1814815 | I7: =IFERROR('Historical FS'!I23/'Historical FS'!H23-1,0) -> 0.50797963 | J7: =IFERROR('Historical FS'!J23/'Historical FS'!I23-1,0) -> 0.060121594 | K7: =IFERROR('Historical FS'!K23/'Historical FS'!J23-1,0) -> 0.062234494 | L7: =IFERROR('Historical FS'!L23/'Historical FS'!K23-1,0) -> 0.50589882 | N7: =IFERROR(AVERAGE(D7:L7),0) -> 0.3064006 | O7: =IFERROR(MEDIAN(D7:L7),0) -> 0.2103294
B8: Net Profit Growth | D8: =IFERROR('Historical FS'!D39/'Historical FS'!C39-1,0) -> 0.58838742 | E8: =IFERROR('Historical FS'!E39/'Historical FS'!D39-1,0) -> 0.24251166 | F8: =IFERROR('Historical FS'!F39/'Historical FS'!E39-1,0) -> 0.068974112 | G8: =IFERROR('Historical FS'!G39/'Historical FS'!F39-1,0) -> -0.35176549 | H8: =IFERROR('Historical FS'!H39/'Historical FS'!G39-1,0) -> 1.2332991 | I8: =IFERROR('Historical FS'!I39/'Historical FS'!H39-1,0) -> 0.49562816 | J8: =IFERROR('Historical FS'!J39/'Historical FS'!I39-1,0) -> 0.075692308 | K8: =IFERROR('Historical FS'!K39/'Historical FS'!J39-1,0) -> -0.045480549 | L8: =IFERROR('Historical FS'!L39/'Historical FS'!K39-1,0) -> 0.52022775 | N8: =IFERROR(AVERAGE(D8:L8),0) -> 0.31416383 | O8: =IFERROR(MEDIAN(D8:L8),0) -> 0.24251166
B9: Dividend Growth | D9: =IFERROR('Historical FS'!D47/'Historical FS'!C47-1,0) -> 0.44227353 | E9: =IFERROR('Historical FS'!E47/'Historical FS'!D47-1,0) -> 0.33335336 | F9: =IFERROR('Historical FS'!F47/'Historical FS'!E47-1,0) -> -0.19801757 | G9: =IFERROR('Historical FS'!G47/'Historical FS'!F47-1,0) -> 0 | H9: =IFERROR('Historical FS'!H47/'Historical FS'!G47-1,0) -> 0.875 | I9: =IFERROR('Historical FS'!I47/'Historical FS'!H47-1,0) -> 0.33003745 | J9: =IFERROR('Historical FS'!J47/'Historical FS'!I47-1,0) -> 0.1 | K9: =IFERROR('Historical FS'!K47/'Historical FS'!J47-1,0) -> 0 | L9: =IFERROR('Historical FS'!L47/'Historical FS'!K47-1,0) -> 0.36363636 | N9: =IFERROR(AVERAGE(D9:L9),0) -> 0.24958702 | O9: =IFERROR(MEDIAN(D9:L9),0) -> 0.33003745
B11: Gross Margin | C11: =IFERROR('Historical FS'!C12,0) -> 0.20020014 | D11: =IFERROR('Historical FS'!D12,0) -> 0.20826228 | E11: =IFERROR('Historical FS'!E12,0) -> 0.20820769 | F11: =IFERROR('Historical FS'!F12,0) -> 0.21024131 | G11: =IFERROR('Historical FS'!G12,0) -> 0.18402329 | H11: =IFERROR('Historical FS'!H12,0) -> 0.19354839 | I11: =IFERROR('Historical FS'!I12,0) -> 0.20406654 | J11: =IFERROR('Historical FS'!J12,0) -> 0.18440216 | ... L11: =IFERROR('Historical FS'!L12,0) -> 0.16125091 | N11: =IFERROR(AVERAGE(C11:L11),0) -> 0.1926758 | O11: =IFERROR(MEDIAN(C11:L11),0) -> 0.19687426
B12: EBITDA Margin | C12: =IFERROR('Historical FS'!C18,0) -> 0.08776977 | D12: =IFERROR('Historical FS'!D18,0) -> 0.10199897 | E12: =IFERROR('Historical FS'!E18,0) -> 0.10080582 | F12: =IFERROR('Historical FS'!F18,0) -> 0.11699601 | G12: =IFERROR('Historical FS'!G18,0) -> 0.079698762 | H12: =IFERROR('Historical FS'!H18,0) -> 0.11611514 | I12: =IFERROR('Historical FS'!I18,0) -> 0.12032039 | J12: =IFERROR('Historical FS'!J18,0) -> 0.10359408 | ... L12: =IFERROR('Historical FS'!L18,0) -> 0.095416971 | N12: =IFERROR(AVERAGE(C12:L12),0) -> 0.10169001 | O12: =IFERROR(MEDIAN(C12:L12),0) -> 0.1014024
B13: EBIT Margin | C13: =IFERROR('Historical FS'!C24,0) -> 0.079434696 | D13: =IFERROR('Historical FS'!D24,0) -> 0.093845632 | E13: =IFERROR('Historical FS'!E24,0) -> 0.09257265 | F13: =IFERROR('Historical FS'!F24,0) -> 0.10046551 | G13: =IFERROR('Historical FS'!G24,0) -> 0.062372944 | H13: =IFERROR('Historical FS'!H24,0) -> 0.1022605 | I13: =IFERROR('Historical FS'!I24,0) -> 0.10945163 | J13: =IFERROR('Historical FS'!J24,0) -> 0.092161929 | ... L13: =IFERROR('Historical FS'!L24,0) -> 0.085986025 | N13: =IFERROR(AVERAGE(C13:L13),0) -> 0.090127284 | O13: =IFERROR(MEDIAN(C13:L13),0) -> 0.092367289
B14: PBT Margin | C14: =IFERROR('Historical FS'!C33,0) -> 0.073392842 | D14: =IFERROR('Historical FS'!D33,0) -> 0.094900858 | E14: =IFERROR('Historical FS'!E33,0) -> 0.098940163 | F14: =IFERROR('Historical FS'!F33,0) -> 0.099847995 | G14: =IFERROR('Historical FS'!G33,0) -> 0.061310294 | H14: =IFERROR('Historical FS'!H33,0) -> 0.10083683 | I14: =IFERROR('Historical FS'!I33,0) -> 0.10959951 | J14: =IFERROR('Historical FS'!J33,0) -> 0.090498003 | ... L14: =IFERROR('Historical FS'!L33,0) -> 0.077651169 | N14: =IFERROR(AVERAGE(C14:L14),0) -> 0.08819909 | O14: =IFERROR(MEDIAN(C14:L14),0) -> 0.092699431
B15: Net Profit Margin | C15: =IFERROR('Historical FS'!C40,0) -> 0.053651996 | D15: =IFERROR('Historical FS'!D40,0) -> 0.070105839 | E15: =IFERROR('Historical FS'!E40,0) -> 0.070993684 | F15: =IFERROR('Historical FS'!F40,0) -> 0.071299639 | G15: =IFERROR('Historical FS'!G40,0) -> 0.044954722 | H15: =IFERROR('Historical FS'!H40,0) -> 0.075454009 | I15: =IFERROR('Historical FS'!I40,0) -> 0.080098583 | J15: =IFERROR('Historical FS'!J40,0) -> 0.068436301 | ... L15: =IFERROR('Historical FS'!L40,0) -> 0.057921538 | N15: =IFERROR(AVERAGE(C15:L15),0) -> 0.064811348 | O15: =IFERROR(MEDIAN(C15:L15),0) -> 0.06927107
B17: SalesExpenses%Sales | C17: =IFERROR('Historical FS'!C15,0) -> 0.11243037 | D17: =IFERROR('Historical FS'!D15,0) -> 0.1062633 | E17: =IFERROR('Historical FS'!E15,0) -> 0.10740187 | F17: =IFERROR('Historical FS'!F15,0) -> 0.093245297 | G17: =IFERROR('Historical FS'!G15,0) -> 0.10432452 | H17: =IFERROR('Historical FS'!H15,0) -> 0.077433244 | I17: =IFERROR('Historical FS'!I15,0) -> 0.083746149 | J17: =IFERROR('Historical FS'!J15,0) -> 0.080808081 | ... L17: =IFERROR('Historical FS'!L15,0) -> 0.065833942 | N17: =IFERROR(AVERAGE(C17:L17),0) -> 0.090985782 | O17: =IFERROR(MEDIAN(C17:L17),0) -> 0.088495723
B18: Depreciation%Sales | C18: =IFERROR('Historical FS'!C21,0) -> 0.008335074 | D18: =IFERROR('Historical FS'!D21,0) -> 0.0081533421 | E18: =IFERROR('Historical FS'!E21,0) -> 0.0082331742 | F18: =IFERROR('Historical FS'!F21,0) -> 0.016530496 | G18: =IFERROR('Historical FS'!G21,0) -> 0.017325818 | H18: =IFERROR('Historical FS'!H21,0) -> 0.013854648 | I18: =IFERROR('Historical FS'!I21,0) -> 0.010868762 | J18: =IFERROR('Historical FS'!J21,0) -> 0.011432151 | ... L18: =IFERROR('Historical FS'!L21,0) -> 0.0094309463 | N18: =IFERROR(AVERAGE(C18:L18),0) -> 0.011562729 | O18: =IFERROR(MEDIAN(C18:L18),0) -> 0.011150456
B19: OperatingIncome%Sales | C19: =C13 -> 0.079434696 | D19: =D13 -> 0.093845632 | E19: =E13 -> 0.09257265 | F19: =F13 -> 0.10046551 | G19: =G13 -> 0.062372944 | H19: =H13 -> 0.1022605 | I19: =I13 -> 0.10945163 | J19: =J13 -> 0.092161929 | ... L19: =L13 -> 0.085986025 | N19: =IFERROR(AVERAGE(C19:L19),0) -> 0.090127284 | O19: =IFERROR(MEDIAN(C19:L19),0) -> 0.092367289
B21: Return on Capital Employed | C21: =IFERROR('Historical FS'!C23/(SUM('Historical FS'!C53:C55)),0) -> 0.17226537 | D21: =IFERROR('Historical FS'!D23/(SUM('Historical FS'!D53:D55)),0) -> 0.22309313 | E21: =IFERROR('Historical FS'!E23/(SUM('Historical FS'!E53:E55)),0) -> 0.21634431 | F21: =IFERROR('Historical FS'!F23/(SUM('Historical FS'!F53:F55)),0) -> 0.20672466 | G21: =IFERROR('Historical FS'!G23/(SUM('Historical FS'!G53:G55)),0) -> 0.10277884 | H21: =IFERROR('Historical FS'!H23/(SUM('Historical FS'!H53:H55)),0) -> 0.17764507 | I21: =IFERROR('Historical FS'!I23/(SUM('Historical FS'!I53:I55)),0) -> 0.20930342 | J21: =IFERROR('Historical FS'!J23/(SUM('Historical FS'!J53:J55)),0) -> 0.18891698 | ... L21: =IFERROR('Historical FS'!L23/(SUM('Historical FS'!L53:L55)),0) -> 0.16257232 | N21: =IFERROR(AVERAGE(C21:L21),0) -> 0.18139912 | O21: =IFERROR(MEDIAN(C21:L21),0) -> 0.18328102
B22: Retained Earnings% | C22: =IFERROR('Historical FS'!C50,0) -> 0.67555905 | D22: =IFERROR('Historical FS'!D50,0) -> 0.70540399 | E22: =IFERROR('Historical FS'!E50,0) -> 0.68386568 | F22: =IFERROR('Historical FS'!F50,0) -> 0.76282478 | G22: =IFERROR('Historical FS'!G50,0) -> 0.63412127 | H22: =IFERROR('Historical FS'!H50,0) -> 0.69282098 | I22: =IFERROR('Historical FS'!I50,0) -> 0.72615385 | J22: =IFERROR('Historical FS'!J50,0) -> 0.71996568 | ... L22: =IFERROR('Historical FS'!L50,0) -> 0.73684211 | N22: =IFERROR(AVERAGE(C22:L22),0) -> 0.70441801 | O22: =IFERROR(MEDIAN(C22:L22),0) -> 0.70601335
B23: Return on Equity% | C23: =IFERROR('Historical FS'!C39/('Historical FS'!C53+'Historical FS'!C54),0) -> 0.16810164 | D23: =IFERROR('Historical FS'!D39/('Historical FS'!D53+'Historical FS'!D54),0) -> 0.22202685 | E23: =IFERROR('Historical FS'!E39/('Historical FS'!E53+'Historical FS'!E54),0) -> 0.23132048 | F23: =IFERROR('Historical FS'!F39/('Historical FS'!F53+'Historical FS'!F54),0) -> 0.22507123 | G23: =IFERROR('Historical FS'!G39/('Historical FS'!G53+'Historical FS'!G54),0) -> 0.12978525 | H23: =IFERROR('Historical FS'!H39/('Historical FS'!H53+'Historical FS'!H54),0) -> 0.23358057 | I23: =IFERROR('Historical FS'!I39/('Historical FS'!I53+'Historical FS'!I54),0) -> 0.27423846 | J23: =IFERROR('Historical FS'!J39/('Historical FS'!J53+'Historical FS'!J54),0) -> 0.37219206 | ... L23: =IFERROR('Historical FS'!L39/('Historical FS'!L53+'Historical FS'!L54),0) -> 0.32305929 | N23: =IFERROR(AVERAGE(C23:L23),0) -> 0.24664543 | O23: =IFERROR(MEDIAN(C23:L23),0) -> 0.23245052
B24: Sustainable Growth Rate | C24: =IFERROR(C22*C23,0) -> 0.11356258 | D24: =IFERROR(D22*D23,0) -> 0.15661862 | E24: =IFERROR(E22*E23,0) -> 0.15819214 | F24: =IFERROR(F22*F23,0) -> 0.17168991 | G24: =IFERROR(G22*G23,0) -> 0.082299587 | H24: =IFERROR(H22*H23,0) -> 0.16182952 | I24: =IFERROR(I22*I23,0) -> 0.19913931 | J24: =IFERROR(J22*J23,0) -> 0.26796551 | ... L24: =IFERROR(L22*L23,0) -> 0.23804369 | N24: =IFERROR(AVERAGE(C24:L24),0) -> 0.1752197 | O24: =IFERROR(MEDIAN(C24:L24),0) -> 0.16675971
B25: Interest Coverage Ratio | C25: =IFERROR('Historical FS'!C23/'Historical FS'!C29,0) -> 27.911235 | D25: =IFERROR('Historical FS'!D23/'Historical FS'!D29,0) -> 28.585979 | E25: =IFERROR('Historical FS'!E23/'Historical FS'!E29,0) -> 34.848687 | F25: =IFERROR('Historical FS'!F23/'Historical FS'!F29,0) -> 12.740964 | G25: =IFERROR('Historical FS'!G23/'Historical FS'!G29,0) -> 6.6502463 | H25: =IFERROR('Historical FS'!H23/'Historical FS'!H29,0) -> 13.509174 | I25: =IFERROR('Historical FS'!I23/'Historical FS'!I29,0) -> 14.803333 | J25: =IFERROR('Historical FS'!J23/'Historical FS'!J29,0) -> 7.6058158 | ... L25: =IFERROR('Historical FS'!L23/'Historical FS'!L29,0) -> 6.3822034 | N25: =IFERROR(AVERAGE(C25:L25),0) -> 15.828528 | O25: =IFERROR(MEDIAN(C25:L25),0) -> 13.125069
B27: Debtor Turnover Ratio | C27: =IFERROR('Historical FS'!C5/'Historical FS'!C65,0) -> 63.87683 | D27: =IFERROR('Historical FS'!D5/'Historical FS'!D65,0) -> 54.515777 | E27: =IFERROR('Historical FS'!E5/'Historical FS'!E65,0) -> 47.041313 | F27: =IFERROR('Historical FS'!F5/'Historical FS'!F65,0) -> 67.474359 | G27: =IFERROR('Historical FS'!G5/'Historical FS'!G65,0) -> 59.136612 | H27: =IFERROR('Historical FS'!H5/'Historical FS'!H65,0) -> 50.971681 | I27: =IFERROR('Historical FS'!I5/'Historical FS'!I65,0) -> 60.200297 | J27: =IFERROR('Historical FS'!J5/'Historical FS'!J65,0) -> 50.180747 | ... L27: =IFERROR('Historical FS'!L5/'Historical FS'!L65,0) -> 95.615721 | N27: =IFERROR(AVERAGE(C27:L27),0) -> 60.562008 | O27: =IFERROR(MEDIAN(C27:L27),0) -> 57.871677
B28: Creditor Turnover Ratio | C28: ='Data Sheet'!B18/'Historical FS'!C114 -> 12.542963 | D28: ='Data Sheet'!C18/'Historical FS'!D114 -> 14.424636 | E28: ='Data Sheet'!D18/'Historical FS'!E114 -> 16.744658 | F28: ='Data Sheet'!E18/'Historical FS'!F114 -> 26.901007 | G28: ='Data Sheet'!F18/'Historical FS'!G114 -> 20.648923 | H28: ='Data Sheet'!G18/'Historical FS'!H114 -> 20.429675 | I28: ='Data Sheet'!H18/'Historical FS'!I114 -> 26.844316 | J28: ='Data Sheet'!I18/'Historical FS'!J114 -> 29.860284 | ... L28: ='Data Sheet'!K18/'Historical FS'!L114 -> 28.017807 | N28: =IFERROR(AVERAGE(C28:L28),0) -> 22.457066 | O28: =IFERROR(MEDIAN(C28:L28),0) -> 23.746619
B29: Inventory Turnover | C29: =IFERROR('Historical FS'!C8/'Historical FS'!C66,0) -> 2.153181 | D29: =IFERROR('Historical FS'!D8/'Historical FS'!D66,0) -> 2.1540885 | E29: =IFERROR('Historical FS'!E8/'Historical FS'!E66,0) -> 2.2248729 | F29: =IFERROR('Historical FS'!F8/'Historical FS'!F66,0) -> 2.0518327 | G29: =IFERROR('Historical FS'!G8/'Historical FS'!G66,0) -> 2.1004995 | H29: =IFERROR('Historical FS'!H8/'Historical FS'!H66,0) -> 1.7065912 | I29: =IFERROR('Historical FS'!I8/'Historical FS'!I66,0) -> 1.9473589 | J29: =IFERROR('Historical FS'!J8/'Historical FS'!J66,0) -> 2.1869718 | ... L29: =IFERROR('Historical FS'!L8/'Historical FS'!L66,0) -> 1.7186674 | N29: =IFERROR(AVERAGE(C29:L29),0) -> 2.0018972 | O29: =IFERROR(MEDIAN(C29:L29),0) -> 2.0761661
B30: Fixed Asset Turnover | C30: =IFERROR('Historical FS'!C5/'Historical FS'!C59,0) -> 11.155554 | D30: =IFERROR('Historical FS'!D5/'Historical FS'!D59,0) -> 10.937482 | E30: =IFERROR('Historical FS'!E5/'Historical FS'!E59,0) -> 12.624883 | F30: =IFERROR('Historical FS'!F5/'Historical FS'!F59,0) -> 7.9954425 | G30: =IFERROR('Historical FS'!G5/'Historical FS'!G59,0) -> 8.5786762 | H30: =IFERROR('Historical FS'!H5/'Historical FS'!H59,0) -> 11.320362 | I30: =IFERROR('Historical FS'!I5/'Historical FS'!I59,0) -> 13.534023 | J30: =IFERROR('Historical FS'!J5/'Historical FS'!J59,0) -> 13.772985 | ... L30: =IFERROR('Historical FS'!L5/'Historical FS'!L59,0) -> 12.733934 | N30: =IFERROR(AVERAGE(C30:L30),0) -> 11.753665 | O30: =IFERROR(MEDIAN(C30:L30),0) -> 11.972622
B31: Capital Turnover Ratio | C31: =IFERROR('Historical FS'!C5/SUM('Historical FS'!C53:C55),0) -> 2.1686414 | D31: =IFERROR('Historical FS'!D5/SUM('Historical FS'!D53:D55),0) -> 2.3772351 | E31: =IFERROR('Historical FS'!E5/SUM('Historical FS'!E53:E55),0) -> 2.3370219 | F31: =IFERROR('Historical FS'!F5/SUM('Historical FS'!F53:F55),0) -> 2.0576679 | G31: =IFERROR('Historical FS'!G5/SUM('Historical FS'!G53:G55),0) -> 1.6478112 | H31: =IFERROR('Historical FS'!H5/SUM('Historical FS'!H53:H55),0) -> 1.7371818 | I31: =IFERROR('Historical FS'!I5/SUM('Historical FS'!I53:I55),0) -> 1.9122915 | J31: =IFERROR('Historical FS'!J5/SUM('Historical FS'!J53:J55),0) -> 2.0498375 | ... L31: =IFERROR('Historical FS'!L5/SUM('Historical FS'!L53:L55),0) -> 1.890683 | N31: =IFERROR(AVERAGE(C31:L31),0) -> 2.004424 | O31: =IFERROR(MEDIAN(C31:L31),0) -> 1.9810645
B33: (In Days)
B34: Debtor Days | C34: =IFERROR(365/C27,0) -> 5.714122 | D34: =IFERROR(365/D27,0) -> 6.6953095 | E34: =IFERROR(365/E27,0) -> 7.7591372 | F34: =IFERROR(365/F27,0) -> 5.4094623 | G34: =IFERROR(365/G27,0) -> 6.1721493 | H34: =IFERROR(365/H27,0) -> 7.1608389 | I34: =IFERROR(365/I27,0) -> 6.063093 | J34: =IFERROR(365/J27,0) -> 7.2737061 | ... L34: =IFERROR(365/L27,0) -> 3.8173639 | N34: =IFERROR(AVERAGE(C34:L34),0) -> 6.2513177 | O34: =IFERROR(MEDIAN(C34:L34),0) -> 6.3100723
B35: Payable Days | C35: =IFERROR(365/C28,0) -> 29.099982 | D35: =IFERROR(365/D28,0) -> 25.303932 | E35: =IFERROR(365/E28,0) -> 21.797997 | F35: =IFERROR(365/F28,0) -> 13.568265 | G35: =IFERROR(365/G28,0) -> 17.676467 | H35: =IFERROR(365/H28,0) -> 17.866167 | I35: =IFERROR(365/I28,0) -> 13.596919 | J35: =IFERROR(365/J28,0) -> 12.223595 | ... L35: =IFERROR(365/L28,0) -> 13.027429 | N35: =IFERROR(AVERAGE(C35:L35),0) -> 17.712406 | O35: =IFERROR(MEDIAN(C35:L35),0) -> 15.636693
B36: Inventory Days | C36: =IFERROR(365/C29,0) -> 169.51663 | D36: =IFERROR(365/D29,0) -> 169.44522 | E36: =IFERROR(365/E29,0) -> 164.05431 | F36: =IFERROR(365/F29,0) -> 177.88975 | G36: =IFERROR(365/G29,0) -> 173.76819 | H36: =IFERROR(365/H29,0) -> 213.87664 | I36: =IFERROR(365/I29,0) -> 187.43335 | J36: =IFERROR(365/J29,0) -> 166.89744 | ... L36: =IFERROR(365/L29,0) -> 212.37384 | N36: =IFERROR(AVERAGE(C36:L36),0) -> 184.08999 | O36: =IFERROR(MEDIAN(C36:L36),0) -> 175.82897
B37: Cash Conversion cycle | C37: =IFERROR(C34+C36-C35,0) -> 146.13077 | D37: =IFERROR(D34+D36-D35,0) -> 150.83659 | E37: =IFERROR(E34+E36-E35,0) -> 150.01545 | F37: =IFERROR(F34+F36-F35,0) -> 169.73095 | G37: =IFERROR(G34+G36-G35,0) -> 162.26387 | H37: =IFERROR(H34+H36-H35,0) -> 203.17131 | I37: =IFERROR(I34+I36-I35,0) -> 179.89952 | J37: =IFERROR(J34+J36-J35,0) -> 161.94755 | ... L37: =IFERROR(L34+L36-L35,0) -> 203.16378 | N37: =IFERROR(AVERAGE(C37:L37),0) -> 172.6289 | O37: =IFERROR(MEDIAN(C37:L37),0) -> 165.99741
B39: CFO/Sales | C39: =IFERROR('Historical FS'!C85/'Historical FS'!C5,0) -> 0.12910202 | D39: =IFERROR('Historical FS'!D85/'Historical FS'!D5,0) -> -0.0031017812 | E39: =IFERROR('Historical FS'!E85/'Historical FS'!E5,0) -> 0.062845956 | F39: =IFERROR('Historical FS'!F85/'Historical FS'!F5,0) -> -0.016530496 | G39: =IFERROR('Historical FS'!G85/'Historical FS'!G5,0) -> 0.19123083 | H39: =IFERROR('Historical FS'!H85/'Historical FS'!H5,0) -> -0.025139762 | I39: =IFERROR('Historical FS'!I85/'Historical FS'!I5,0) -> 0.033764633 | J39: =IFERROR('Historical FS'!J85/'Historical FS'!J5,0) -> 0.033180644 | ... L39: =IFERROR('Historical FS'!L85/'Historical FS'!L5,0) -> 0.063824443 | N39: =IFERROR(AVERAGE(C39:L39),0) -> 0.046022783 | O39: =IFERROR(MEDIAN(C39:L39),0) -> 0.033472639
B40: CFO/Total Assets | C40: =IFERROR('Historical FS'!C85/'Historical FS'!C70,0) -> 0.20362602 | D40: =IFERROR('Historical FS'!D85/'Historical FS'!D70,0) -> -0.0052515271 | E40: =IFERROR('Historical FS'!E85/'Historical FS'!E70,0) -> 0.10615004 | F40: =IFERROR('Historical FS'!F85/'Historical FS'!F70,0) -> -0.025694034 | G40: =IFERROR('Historical FS'!G85/'Historical FS'!G70,0) -> 0.25170275 | H40: =IFERROR('Historical FS'!H85/'Historical FS'!H70,0) -> -0.034170285 | I40: =IFERROR('Historical FS'!I85/'Historical FS'!I70,0) -> 0.050703183 | J40: =IFERROR('Historical FS'!J85/'Historical FS'!J70,0) -> 0.053729356 | ... L40: =IFERROR('Historical FS'!L85/'Historical FS'!L70,0) -> 0.092303628 | N40: =IFERROR(AVERAGE(C40:L40),0) -> 0.067978876 | O40: =IFERROR(MEDIAN(C40:L40),0) -> 0.05221627
B41: CFO/Total Debt | C41: =IFERROR('Historical FS'!C85/'Historical FS'!C55,0) -> 0.90946277 | D41: =IFERROR('Historical FS'!D85/'Historical FS'!D55,0) -> -0.029568128 | E41: =IFERROR('Historical FS'!E85/'Historical FS'!E55,0) -> 0.51943602 | F41: =IFERROR('Historical FS'!F85/'Historical FS'!F55,0) -> -0.097697923 | G41: =IFERROR('Historical FS'!G85/'Historical FS'!G55,0) -> 0.73412558 | H41: =IFERROR('Historical FS'!H85/'Historical FS'!H55,0) -> -0.0995189 | I41: =IFERROR('Historical FS'!I85/'Historical FS'!I55,0) -> 0.14625814 | J41: =IFERROR('Historical FS'!J85/'Historical FS'!J55,0) -> 0.10915765 | ... L41: =IFERROR('Historical FS'!L85/'Historical FS'!L55,0) -> 0.18255446 | N41: =IFERROR(AVERAGE(C41:L41),0) -> 0.23481713 | O41: =IFERROR(MEDIAN(C41:L41),0) -> 0.1277079

Sheet Projections 
B2: ='Data Sheet'!$B$1& " - " &'Data Sheet'!A17& " Forecast 3 Methods" -> TITAN COMPANY LTD - Sales Forecast 3 Methods
B4: Year Weight | C4: 1 | D4: =C4+1 -> 2 | E4: =D4+1 -> 3 | F4: =E4+1 -> 4 | G4: =F4+1 -> 5 | H4: =G4+1 -> 6 | I4: =H4+1 -> 7 | J4: =I4+1 -> 8 | K4: =J4+1 -> 9 | ... R4: =Q4+1 -> 16
B5: ='Historical FS'!B3 -> Years | C5: ='Historical FS'!C3 -> 42825 | D5: ='Historical FS'!D3 -> 43190 | E5: ='Historical FS'!E3 -> 43555 | F5: ='Historical FS'!F3 -> 43921 | G5: ='Historical FS'!G3 -> 44286 | H5: ='Historical FS'!H3 -> 44651 | I5: ='Historical FS'!I3 -> 45016 | ... L5: ='Historical FS'!L3 -> 46112 | M5: =L5+365 -> 46477 | N5: =M5+365 -> 46842 | O5: =N5+365 -> 47207 | P5: =O5+365 -> 47572 | Q5: =P5+365 -> 47937 | R5: =Q5+365 -> 48302
B6: ='Historical FS'!B5 -> Sales | C6: ='Historical FS'!C5 -> 13260.83 | D6: ='Historical FS'!D5 -> 16119.77 | E6: ='Historical FS'!E5 -> 19778.52 | F6: ='Historical FS'!F5 -> 21052 | G6: ='Historical FS'!G5 -> 21644 | H6: ='Historical FS'!H5 -> 28799 | I6: ='Historical FS'!I5 -> 40575 | ... L6: ='Historical FS'!L5 -> 87584 | M6: {=_xlfn.XLOOKUP(F15,B19:B21,M19:R21,"Error",0)} -> 108023.86 | N6: 133233.85 | O6: 164327.2 | P6: 202676.95 | Q6: 249976.54 | R6: 308314.65
B7: ='Historical FS'!B6 -> Sales Growth | D7: =D6/C6-1 -> 0.21559284 | E7: =E6/D6-1 -> 0.22697284 | F7: =F6/E6-1 -> 0.064387022 | G7: =G6/F6-1 -> 0.028120844 | H7: =H6/G6-1 -> 0.3305766 | I7: =I6/H6-1 -> 0.40890309 | J7: =J6/I6-1 -> 0.25900185 | K7: =K6/J6-1 -> 0.18346253 | ... R7: =R6/Q6-1 -> 0.2333743
B9: Growth Rate Methods (single implied annual rate)
B11: Arithmetic Mean of YoY Growth (FY18-FY26) | F11: =AVERAGE($D$7:$L$7) -> 0.24063785
B12: Geometric Mean / CAGR (FY17-FY26) | F12: =_xlfn.RRI($L$4-1,$C$6,$L$6) -> 0.2333743
B13: Log-Linear Regression (implied CAGR) | F13: {=EXP(SLOPE(LN($C$6:$L$6),$C$4:$L$4))-1} -> 0.22319246
B15: Select Method for Forecast | F15: Geometric Mean method
B17: Sales Forecast by Method (₹ Cr)
B19: Arithmetic Mean method | M19: =L6*(1+$F$11) -> 108660.03 | N19: =M19*(1+$F$11) -> 134807.74 | O19: =N19*(1+$F$11) -> 167247.59 | P19: =O19*(1+$F$11) -> 207493.68 | Q19: =P19*(1+$F$11) -> 257424.52 | R19: =Q19*(1+$F$11) -> 319370.6
B20: Geometric Mean method | M20: =$L$6*(1+$F$12) -> 108023.86 | N20: =M20*(1+$F$12) -> 133233.85 | O20: =N20*(1+$F$12) -> 164327.2 | P20: =O20*(1+$F$12) -> 202676.95 | Q20: =P20*(1+$F$12) -> 249976.54 | R20: =Q20*(1+$F$12) -> 308314.65
B21: Log-Linear Regression method | M21: =$L$6*(1+$F$13) -> 107132.09 | N21: =M21*(1+$F$13) -> 131043.16 | O21: =N21*(1+$F$13) -> 160291.01 | P21: =O21*(1+$F$13) -> 196066.76 | Q21: =P21*(1+$F$13) -> 239827.38 | R21: =Q21*(1+$F$13) -> 293355.04
B24: ='Data Sheet'!$B$1& " - " &'Historical FS'!B17& " Forecast 3 Methods" -> TITAN COMPANY LTD - EBITDA Forecast 3 Methods
B26: Year Weight | C26: 1 | D26: =C26+1 -> 2 | E26: =D26+1 -> 3 | F26: =E26+1 -> 4 | G26: =F26+1 -> 5 | H26: =G26+1 -> 6 | I26: =H26+1 -> 7 | J26: =I26+1 -> 8 | K26: =J26+1 -> 9 | ... R26: =Q26+1 -> 16
B27: ='Historical FS'!B3 -> Years | C27: ='Historical FS'!C3 -> 42825 | D27: ='Historical FS'!D3 -> 43190 | E27: ='Historical FS'!E3 -> 43555 | F27: ='Historical FS'!F3 -> 43921 | G27: ='Historical FS'!G3 -> 44286 | H27: ='Historical FS'!H3 -> 44651 | I27: ='Historical FS'!I3 -> 45016 | ... L27: ='Historical FS'!L3 -> 46112 | M27: =L27+365 -> 46477 | N27: =M27+365 -> 46842 | O27: =N27+365 -> 47207 | P27: =O27+365 -> 47572 | Q27: =P27+365 -> 47937 | R27: =Q27+365 -> 48302
B28: EBITDA | C28: ='Historical FS'!C17 -> 1163.9 | D28: ='Historical FS'!D17 -> 1644.2 | E28: ='Historical FS'!E17 -> 1993.79 | F28: ='Historical FS'!F17 -> 2463 | G28: ='Historical FS'!G17 -> 1725 | H28: ='Historical FS'!H17 -> 3344 | I28: ='Historical FS'!I17 -> 4882 | J28: ='Historical FS'!J17 -> 5292 | ... L28: ='Historical FS'!L17 -> 8357 | M28: {=_xlfn.XLOOKUP(F38,B42:B44,M42:R44,"Error",0)} -> 10403.428 | N28: 12950.978 | O28: 16122.361 | P28: 20070.34 | Q28: 24985.084 | R28: 31103.33
B29: ='Historical FS'!B18 -> EBITDA Margins | C29: =C28/C6 -> 0.08776977 | D29: =D28/D6 -> 0.10199897 | E29: =E28/E6 -> 0.10080582 | F29: =F28/F6 -> 0.11699601 | G29: =G28/G6 -> 0.079698762 | H29: =H28/H6 -> 0.11611514 | I29: =I28/I6 -> 0.12032039 | J29: =J28/J6 -> 0.10359408 | ... R29: =R28/R6 -> 0.10088178
B30: EBITDA Growth | D30: =D28/C28-1 -> 0.41266432 | E30: =E28/D28-1 -> 0.21262012 | F30: =F28/E28-1 -> 0.23533572 | G30: =G28/F28-1 -> -0.29963459 | H30: =H28/G28-1 -> 0.93855072 | I30: =I28/H28-1 -> 0.45992823 | J30: =J28/I28-1 -> 0.083981975 | K30: =K28/J28-1 -> 0.075963719 | ... R30: =R28/Q28-1 -> 0.24487596
B32: Growth Rate Methods (single implied annual rate)
B34: Arithmetic Mean of YoY EBITDA Growth (FY18-FY26) | F34: =AVERAGE($D$30:$L$30) -> 0.28745505
B35: Geometric Mean / CAGR (FY17-FY26) | F35: =_xlfn.RRI($L$26-1,$C$28,$L$28) -> 0.24487596
B36: Log-Linear Regression (implied CAGR) | F36: {=EXP(SLOPE(LN($C$28:$L$28),$C$26:$L$26))-1} -> 0.22906811
B38: Select Method for Forecast | F38: Geometric Mean method
B40: EBITDA Forecast by Method (₹ Cr)
B42: Arithmetic Mean method | M42: =$L$28*(1+$F$34) -> 10759.262 | N42: =M42*(1+$F$34) -> 13852.066 | O42: =N42*(1+$F$34) -> 17833.913 | P42: =O42*(1+$F$34) -> 22960.361 | Q42: =P42*(1+$F$34) -> 29560.433 | R42: =Q42*(1+$F$34) -> 38057.728
B43: Geometric Mean method | M43: =$L$28*(1+$F$35) -> 10403.428 | N43: =M43*(1+$F$35) -> 12950.978 | O43: =N43*(1+$F$35) -> 16122.361 | P43: =O43*(1+$F$35) -> 20070.34 | Q43: =P43*(1+$F$35) -> 24985.084 | R43: =Q43*(1+$F$35) -> 31103.33
B44: Log-Linear Regression method | M44: =$L$28*(1+$F$36) -> 10271.322 | N44: =M44*(1+$F$36) -> 12624.155 | O44: =N44*(1+$F$36) -> 15515.946 | P44: =O44*(1+$F$36) -> 19070.154 | Q44: =P44*(1+$F$36) -> 23438.518 | R44: =Q44*(1+$F$36) -> 28807.535

Sheet Sensitivity Analysis
B2: Base Case | G2: FY27
B3: Sales Growth Rate | G3: ='Projections '!$M$7 -> 0.2333743
B4: EBITDA Margin | G4: ='Projections '!$M$29 -> 0.096306769
B6: Base Sales at Base Growth Rate for FY27 | G6: ='Projections '!$L$6*(1+$G$3) -> 108023.86
B7: FY27 EBITDA - Base Case Output | G7: =G6*G4 -> 10403.428
B9: Senstivity Analysis
B10: Senstivity to Sales Growth and EBITDA margin
B12: =G7 -> 10403.428 | C12: =D12-0.05 -> 0.1333743 | D12: =E12-0.05 -> 0.1833743 | E12: ='Projections '!$M$7 -> 0.2333743 | F12: =E12+0.05 -> 0.2833743 | G12: =F12+0.05 -> 0.3333743
B13: =B14-0.02 -> 0.056306769 | C13: 5589.317 | D13: 5835.8956 | E13: 6082.4742 | F13: 6329.0528 | G13: 6575.6314
B14: =B15-0.02 -> 0.076306769 | C14: 7574.6261 | D14: 7908.7887 | E14: 8242.9513 | F14: 8577.1139 | G14: 8911.2765
B15: ='Projections '!$M$29 -> 0.096306769 | C15: 9559.9352 | D15: 9981.6818 | E15: 10403.428 | F15: 10825.175 | G15: 11246.922
B16: =B15+0.02 -> 0.11630677 | C16: 11545.244 | D16: 12054.575 | E16: 12563.906 | F16: 13073.236 | G16: 13582.567
B17: =B16+0.02 -> 0.13630677 | C17: 13530.553 | D17: 14127.468 | E17: 14724.383 | F17: 15321.297 | G17: 15918.212
B19: Range: | C19: ="₹"&TEXT(MIN(C13:G17),"#,##0")&"- ₹"&TEXT(MAX(C13:G17),"#,##0") -> ₹5,589- ₹15,918
B20: Vs Base : | C20: =TEXT((C13-E15)/E15,"+0%;-0%")& " / " &TEXT((G17-E15)/E15,"+0%;-0%") -> -46% / +53%
